[
	{
		"time": "20180131",
		"title": "为什么浪漫无法持久？",
		"downUrl": "http://txly2.net/ly/audio/2018/se/se180131.mp3",
		"duration": 1760,
		"size": "14.1M",
		"artistId": 19,
		"artistName": "恋爱季节",
		"path": "https://rawcdn.githack.com/quiet324/LiangYouRadioResource201805/se20180131/se/se180131.mp3",
		"id": 19180131
	},
	{
		"time": "20180201",
		"title": "把浪漫带入你的婚姻（1）",
		"downUrl": "http://txly2.net/ly/audio/2018/se/se180201.mp3",
		"duration": 1760,
		"size": "14.1M",
		"artistId": 19,
		"artistName": "恋爱季节",
		"path": "https://rawcdn.githack.com/quiet324/LiangYouRadioResource201805/se20180201/se/se180201.mp3",
		"id": 19180201
	},
	{
		"time": "20180202",
		"title": "如何处理婚姻生活中与亲属邻里之间的关系？",
		"downUrl": "http://txly2.net/ly/audio/2018/se/se180202.mp3",
		"duration": 1760,
		"size": "14.1M",
		"artistId": 19,
		"artistName": "恋爱季节",
		"path": "https://rawcdn.githack.com/quiet324/LiangYouRadioResource201805/se20180202/se/se180202.mp3",
		"id": 19180202
	},
	{
		"time": "20180205",
		"title": "把浪漫带入你的婚姻（下）",
		"downUrl": "http://txly2.net/ly/audio/2018/se/se180205.mp3",
		"duration": 1760,
		"size": "14.1M",
		"artistId": 19,
		"artistName": "恋爱季节",
		"path": "https://rawcdn.githack.com/quiet324/LiangYouRadioResource201806/se20180205/se/se180205.mp3",
		"id": 19180205
	},
	{
		"time": "20180206",
		"title": "检视婚姻中的生活步调",
		"downUrl": "http://txly2.net/ly/audio/2018/se/se180206.mp3",
		"duration": 1760,
		"size": "14.1M",
		"artistId": 19,
		"artistName": "恋爱季节",
		"path": "https://rawcdn.githack.com/quiet324/LiangYouRadioResource201806/se20180206/se/se180206.mp3",
		"id": 19180206
	},
	{
		"time": "20180207",
		"title": "在婚姻中找到真实的你",
		"downUrl": "http://txly2.net/ly/audio/2018/se/se180207.mp3",
		"duration": 1760,
		"size": "14.1M",
		"artistId": 19,
		"artistName": "恋爱季节",
		"path": "https://rawcdn.githack.com/quiet324/LiangYouRadioResource201806/se20180207/se/se180207.mp3",
		"id": 19180207
	},
	{
		"time": "20180208",
		"title": "坚守婚姻，持续学习，不断成长",
		"downUrl": "http://txly2.net/ly/audio/2018/se/se180208.mp3",
		"duration": 1760,
		"size": "14.1M",
		"artistId": 19,
		"artistName": "恋爱季节",
		"path": "https://rawcdn.githack.com/quiet324/LiangYouRadioResource201806/se20180208/se/se180208.mp3",
		"id": 19180208
	},
	{
		"time": "20180209",
		"title": "作父母的面临女儿要搬出去与男友同居，该怎么办？什么才是正确的婚姻观？",
		"downUrl": "http://txly2.net/ly/audio/2018/se/se180209.mp3",
		"duration": 1760,
		"size": "14.1M",
		"artistId": 19,
		"artistName": "恋爱季节",
		"path": "https://rawcdn.githack.com/quiet324/LiangYouRadioResource201806/se20180209/se/se180209.mp3",
		"id": 19180209
	},
	{
		"time": "20180209",
		"title": "作父母的面临女儿要搬出去与男友同居，该怎么办？什么才是正确的婚姻观？",
		"downUrl": "http://txly2.net/ly/audio/2018/se/se180209.mp3",
		"duration": 1760,
		"size": "14.1M",
		"artistId": 19,
		"artistName": "恋爱季节",
		"path": "https://rawcdn.githack.com/quiet324/LiangYouRadioResource201807/se20180209/se/se180209.mp3",
		"id": 19180209
	},
	{
		"time": "20180216",
		"title": "我适合结婚吗？如何开始一段认识异性的机会？",
		"downUrl": "http://txly2.net/ly/audio/2018/se/se180216.mp3",
		"duration": 1760,
		"size": "14.1M",
		"artistId": 19,
		"artistName": "恋爱季节",
		"path": "https://rawcdn.githack.com/quiet324/LiangYouRadioResource201807/se20180216/se/se180216.mp3",
		"id": 19180216
	},
	{
		"time": "20180215",
		"title": "谈恋爱以前要做“分手”的准备？",
		"downUrl": "http://txly2.net/ly/audio/2018/se/se180215.mp3",
		"duration": 1760,
		"size": "14.1M",
		"artistId": 19,
		"artistName": "恋爱季节",
		"path": "https://rawcdn.githack.com/quiet324/LiangYouRadioResource201807/se20180215/se/se180215.mp3",
		"id": 19180215
	},
	{
		"time": "20180214",
		"title": "亲密关系分级制（2）",
		"downUrl": "http://txly2.net/ly/audio/2018/se/se180214.mp3",
		"duration": 1760,
		"size": "14.1M",
		"artistId": 19,
		"artistName": "恋爱季节",
		"path": "https://rawcdn.githack.com/quiet324/LiangYouRadioResource201807/se20180214/se/se180214.mp3",
		"id": 19180214
	},
	{
		"time": "20180213",
		"title": "亲密关系分级制（1）",
		"downUrl": "http://txly2.net/ly/audio/2018/se/se180213.mp3",
		"duration": 1760,
		"size": "14.1M",
		"artistId": 19,
		"artistName": "恋爱季节",
		"path": "https://rawcdn.githack.com/quiet324/LiangYouRadioResource201807/se20180213/se/se180213.mp3",
		"id": 19180213
	},
	{
		"time": "20180212",
		"title": "问世间情为何物？",
		"downUrl": "http://txly2.net/ly/audio/2018/se/se180212.mp3",
		"duration": 1760,
		"size": "14.1M",
		"artistId": 19,
		"artistName": "恋爱季节",
		"path": "https://rawcdn.githack.com/quiet324/LiangYouRadioResource201807/se20180212/se/se180212.mp3",
		"id": 19180212
	},
	{
		"time": "20180219",
		"title": "背起感情十字架，走向你的各各他",
		"downUrl": "http://txly2.net/ly/audio/2018/se/se180219.mp3",
		"duration": 1760,
		"size": "14.1M",
		"artistId": 19,
		"artistName": "恋爱季节",
		"path": "https://rawcdn.githack.com/quiet324/LiangYouRadioResource201808/se20180219/se/se180219.mp3",
		"id": 19180219
	},
	{
		"time": "20180220",
		"title": "谈谈婚前性行为",
		"downUrl": "http://txly2.net/ly/audio/2018/se/se180220.mp3",
		"duration": 1760,
		"size": "14.1M",
		"artistId": 19,
		"artistName": "恋爱季节",
		"path": "https://rawcdn.githack.com/quiet324/LiangYouRadioResource201808/se20180220/se/se180220.mp3",
		"id": 19180220
	},
	{
		"time": "20180221",
		"title": "我的情人在哪里？",
		"downUrl": "http://txly2.net/ly/audio/2018/se/se180221.mp3",
		"duration": 1760,
		"size": "14.1M",
		"artistId": 19,
		"artistName": "恋爱季节",
		"path": "https://rawcdn.githack.com/quiet324/LiangYouRadioResource201808/se20180221/se/se180221.mp3",
		"id": 19180221
	},
	{
		"time": "20180222",
		"title": "谈谈浪漫",
		"downUrl": "http://txly2.net/ly/audio/2018/se/se180222.mp3",
		"duration": 1760,
		"size": "14.1M",
		"artistId": 19,
		"artistName": "恋爱季节",
		"path": "https://rawcdn.githack.com/quiet324/LiangYouRadioResource201808/se20180222/se/se180222.mp3",
		"id": 19180222
	},
	{
		"time": "20180223",
		"title": "择偶时应该注意哪些方面？从法律观点谈婚姻等相关问题",
		"downUrl": "http://txly2.net/ly/audio/2018/se/se180223.mp3",
		"duration": 1760,
		"size": "14.1M",
		"artistId": 19,
		"artistName": "恋爱季节",
		"path": "https://rawcdn.githack.com/quiet324/LiangYouRadioResource201808/se20180223/se/se180223.mp3",
		"id": 19180223
	},
	{
		"time": "20180302",
		"title": "约会应有的正确态度和功能有哪些？婚后也需要约会吗？",
		"downUrl": "http://txly2.net/ly/audio/2018/se/se180302.mp3",
		"duration": 1760,
		"size": "14.1M",
		"artistId": 19,
		"artistName": "恋爱季节",
		"path": "https://rawcdn.githack.com/quiet324/LiangYouRadioResource201810/se20180302/se/se180302.mp3",
		"id": 19180302
	},
	{
		"time": "20180301",
		"title": "爱不是占有，也不是放手",
		"downUrl": "http://txly2.net/ly/audio/2018/se/se180301.mp3",
		"duration": 1760,
		"size": "14.1M",
		"artistId": 19,
		"artistName": "恋爱季节",
		"path": "https://rawcdn.githack.com/quiet324/LiangYouRadioResource201810/se20180301/se/se180301.mp3",
		"id": 19180301
	},
	{
		"time": "20180228",
		"title": "你永远到不了对方的内心世界",
		"downUrl": "http://txly2.net/ly/audio/2018/se/se180228.mp3",
		"duration": 1760,
		"size": "14.1M",
		"artistId": 19,
		"artistName": "恋爱季节",
		"path": "https://rawcdn.githack.com/quiet324/LiangYouRadioResource201810/se20180228/se/se180228.mp3",
		"id": 19180228
	},
	{
		"time": "20180227",
		"title": "耶稣为何不结婚？",
		"downUrl": "http://txly2.net/ly/audio/2018/se/se180227.mp3",
		"duration": 1760,
		"size": "14.1M",
		"artistId": 19,
		"artistName": "恋爱季节",
		"path": "https://rawcdn.githack.com/quiet324/LiangYouRadioResource201810/se20180227/se/se180227.mp3",
		"id": 19180227
	},
	{
		"time": "20180226",
		"title": "婚姻是怎么配合的？",
		"downUrl": "http://txly2.net/ly/audio/2018/se/se180226.mp3",
		"duration": 1760,
		"size": "14.1M",
		"artistId": 19,
		"artistName": "恋爱季节",
		"path": "https://rawcdn.githack.com/quiet324/LiangYouRadioResource201810/se20180226/se/se180226.mp3",
		"id": 19180226
	},
	{
		"time": "20180305",
		"title": "爱上不该爱的人（1）",
		"downUrl": "http://txly2.net/ly/audio/2018/se/se180305.mp3",
		"duration": 1760,
		"size": "14.1M",
		"artistId": 19,
		"artistName": "恋爱季节",
		"path": "https://rawcdn.githack.com/quiet324/LiangYouRadioResource201810/se20180305/se/se180305.mp3",
		"id": 19180305
	},
	{
		"time": "20180306",
		"title": "爱上不该爱的人（2）",
		"downUrl": "http://txly2.net/ly/audio/2018/se/se180306.mp3",
		"duration": 1760,
		"size": "14.1M",
		"artistId": 19,
		"artistName": "恋爱季节",
		"path": "https://rawcdn.githack.com/quiet324/LiangYouRadioResource201810/se20180306/se/se180306.mp3",
		"id": 19180306
	},
	{
		"time": "20180307",
		"title": "爱上不该爱的人（3）",
		"downUrl": "http://txly2.net/ly/audio/2018/se/se180307.mp3",
		"duration": 1760,
		"size": "14.1M",
		"artistId": 19,
		"artistName": "恋爱季节",
		"path": "https://rawcdn.githack.com/quiet324/LiangYouRadioResource201810/se20180307/se/se180307.mp3",
		"id": 19180307
	},
	{
		"time": "20180308",
		"title": "真感情与假婚姻的无情对决",
		"downUrl": "http://txly2.net/ly/audio/2018/se/se180308.mp3",
		"duration": 1760,
		"size": "14.1M",
		"artistId": 19,
		"artistName": "恋爱季节",
		"path": "https://rawcdn.githack.com/quiet324/LiangYouRadioResource201810/se20180308/se/se180308.mp3",
		"id": 19180308
	},
	{
		"time": "20180309",
		"title": "夫妻间沟通如何能说的清楚又听的明白？",
		"downUrl": "http://txly2.net/ly/audio/2018/se/se180309.mp3",
		"duration": 1760,
		"size": "14.1M",
		"artistId": 19,
		"artistName": "恋爱季节",
		"path": "https://rawcdn.githack.com/quiet324/LiangYouRadioResource201810/se20180309/se/se180309.mp3",
		"id": 19180309
	},
	{
		"time": "20180312",
		"title": "家的十大功能",
		"downUrl": "http://txly2.net/ly/audio/2018/se/se180312.mp3",
		"duration": 1760,
		"size": "14.1M",
		"artistId": 19,
		"artistName": "恋爱季节",
		"path": "https://rawcdn.githack.com/quiet324/LiangYouRadioResource201811/se20180312/se/se180312.mp3",
		"id": 19180312
	},
	{
		"time": "20180313",
		"title": "你的家还好吗？",
		"downUrl": "http://txly2.net/ly/audio/2018/se/se180313.mp3",
		"duration": 1760,
		"size": "14.1M",
		"artistId": 19,
		"artistName": "恋爱季节",
		"path": "https://rawcdn.githack.com/quiet324/LiangYouRadioResource201811/se20180313/se/se180313.mp3",
		"id": 19180313
	},
	{
		"time": "20180314",
		"title": "家和万事兴",
		"downUrl": "http://txly2.net/ly/audio/2018/se/se180314.mp3",
		"duration": 1760,
		"size": "14.1M",
		"artistId": 19,
		"artistName": "恋爱季节",
		"path": "https://rawcdn.githack.com/quiet324/LiangYouRadioResource201811/se20180314/se/se180314.mp3",
		"id": 19180314
	},
	{
		"time": "20180315",
		"title": "冷漠背后的真相",
		"downUrl": "http://txly2.net/ly/audio/2018/se/se180315.mp3",
		"duration": 1760,
		"size": "14.1M",
		"artistId": 19,
		"artistName": "恋爱季节",
		"path": "https://rawcdn.githack.com/quiet324/LiangYouRadioResource201811/se20180315/se/se180315.mp3",
		"id": 19180315
	},
	{
		"time": "20180316",
		"title": "什么是夫妻间沟通的基本技巧？",
		"downUrl": "http://txly2.net/ly/audio/2018/se/se180316.mp3",
		"duration": 1760,
		"size": "14.1M",
		"artistId": 19,
		"artistName": "恋爱季节",
		"path": "https://rawcdn.githack.com/quiet324/LiangYouRadioResource201811/se20180316/se/se180316.mp3",
		"id": 19180316
	},
	{
		"time": "20180319",
		"title": "爱情是什么？",
		"downUrl": "http://txly2.net/ly/audio/2018/se/se180319.mp3",
		"duration": 1760,
		"size": "14.1M",
		"artistId": 19,
		"artistName": "恋爱季节",
		"path": "https://rawcdn.githack.com/quiet324/LiangYouRadioResource201813/se20180319/se/se180319.mp3",
		"id": 19180319
	},
	{
		"time": "20180320",
		"title": "圣经的婚姻观（1）离开父母（上）",
		"downUrl": "http://txly2.net/ly/audio/2018/se/se180320.mp3",
		"duration": 1760,
		"size": "14.1M",
		"artistId": 19,
		"artistName": "恋爱季节",
		"path": "https://rawcdn.githack.com/quiet324/LiangYouRadioResource201813/se20180320/se/se180320.mp3",
		"id": 19180320
	},
	{
		"time": "20180321",
		"title": "圣经的婚姻观（2）离开父母（下）",
		"downUrl": "http://txly2.net/ly/audio/2018/se/se180321.mp3",
		"duration": 1760,
		"size": "14.1M",
		"artistId": 19,
		"artistName": "恋爱季节",
		"path": "https://rawcdn.githack.com/quiet324/LiangYouRadioResource201813/se20180321/se/se180321.mp3",
		"id": 19180321
	},
	{
		"time": "20180322",
		"title": "圣经的婚姻观（3）与妻子连合，二人成为一体",
		"downUrl": "http://txly2.net/ly/audio/2018/se/se180322.mp3",
		"duration": 1760,
		"size": "14.1M",
		"artistId": 19,
		"artistName": "恋爱季节",
		"path": "https://rawcdn.githack.com/quiet324/LiangYouRadioResource201813/se20180322/se/se180322.mp3",
		"id": 19180322
	},
	{
		"time": "20180323",
		"title": "如何多了解男女之间不同，使婚姻更美好？",
		"downUrl": "http://txly2.net/ly/audio/2018/se/se180323.mp3",
		"duration": 1760,
		"size": "14.1M",
		"artistId": 19,
		"artistName": "恋爱季节",
		"path": "https://rawcdn.githack.com/quiet324/LiangYouRadioResource201813/se20180323/se/se180323.mp3",
		"id": 19180323
	},
	{
		"time": "20180326",
		"title": "上帝所配合的，人不可分开。",
		"downUrl": "http://txly2.net/ly/audio/2018/se/se180326.mp3",
		"duration": 1760,
		"size": "14.1M",
		"artistId": 19,
		"artistName": "恋爱季节",
		"path": "https://rawcdn.githack.com/quiet324/LiangYouRadioResource201813/se20180326/se/se180326.mp3",
		"id": 19180326
	},
	{
		"time": "20180327",
		"title": "你们不信的原不相配，不要同负一轭。",
		"downUrl": "http://txly2.net/ly/audio/2018/se/se180327.mp3",
		"duration": 1760,
		"size": "14.1M",
		"artistId": 19,
		"artistName": "恋爱季节",
		"path": "https://rawcdn.githack.com/quiet324/LiangYouRadioResource201813/se20180327/se/se180327.mp3",
		"id": 19180327
	},
	{
		"time": "20180328",
		"title": "丈夫是妻子的头──要爱妻子，正如基督爱教会。",
		"downUrl": "http://txly2.net/ly/audio/2018/se/se180328.mp3",
		"duration": 1760,
		"size": "14.1M",
		"artistId": 19,
		"artistName": "恋爱季节",
		"path": "https://rawcdn.githack.com/quiet324/LiangYouRadioResource201813/se20180328/se/se180328.mp3",
		"id": 19180328
	},
	{
		"time": "20180329",
		"title": "做妻子的当顺服自己的丈夫，如同顺服主。",
		"downUrl": "http://txly2.net/ly/audio/2018/se/se180329.mp3",
		"duration": 1760,
		"size": "14.1M",
		"artistId": 19,
		"artistName": "恋爱季节",
		"path": "https://rawcdn.githack.com/quiet324/LiangYouRadioResource201813/se20180329/se/se180329.mp3",
		"id": 19180329
	},
	{
		"time": "20180330",
		"title": "丈夫该明白妻子哪些需求，使婚姻更美满？",
		"downUrl": "http://txly2.net/ly/audio/2018/se/se180330.mp3",
		"duration": 1760,
		"size": "14.1M",
		"artistId": 19,
		"artistName": "恋爱季节",
		"path": "https://rawcdn.githack.com/quiet324/LiangYouRadioResource201813/se20180330/se/se180330.mp3",
		"id": 19180330
	},
	{
		"time": "20180403",
		"title": "誓约是双向的",
		"downUrl": "http://txly2.net/ly/audio/2018/se/se180403.mp3",
		"duration": 1760,
		"size": "14.1M",
		"artistId": 19,
		"artistName": "恋爱季节",
		"path": "https://rawcdn.githack.com/quiet324/LiangYouRadioResource201814/se20180403/se/se180403.mp3",
		"id": 19180403
	},
	{
		"time": "20180402",
		"title": "婚姻誓言的五项重要特质",
		"downUrl": "http://txly2.net/ly/audio/2018/se/se180402.mp3",
		"duration": 1760,
		"size": "14.1M",
		"artistId": 19,
		"artistName": "恋爱季节",
		"path": "https://rawcdn.githack.com/quiet324/LiangYouRadioResource201814/se20180402/se/se180402.mp3",
		"id": 19180402
	},
	{
		"time": "20180404",
		"title": "拆除沟通障碍，让我们都坦诚",
		"downUrl": "http://txly2.net/ly/audio/2018/se/se180404.mp3",
		"duration": 1760,
		"size": "14.1M",
		"artistId": 19,
		"artistName": "恋爱季节",
		"path": "https://rawcdn.githack.com/quiet324/LiangYouRadioResource201814/se20180404/se/se180404.mp3",
		"id": 19180404
	},
	{
		"time": "20180405",
		"title": "从祷告中学会心灵沟通",
		"downUrl": "http://txly2.net/ly/audio/2018/se/se180405.mp3",
		"duration": 1760,
		"size": "14.1M",
		"artistId": 19,
		"artistName": "恋爱季节",
		"path": "https://rawcdn.githack.com/quiet324/LiangYouRadioResource201814/se20180405/se/se180405.mp3",
		"id": 19180405
	},
	{
		"time": "20180406",
		"title": "妻子该明白丈夫哪些需求，使婚姻更幸福？",
		"downUrl": "http://txly2.net/ly/audio/2018/se/se180406.mp3",
		"duration": 1760,
		"size": "14.1M",
		"artistId": 19,
		"artistName": "恋爱季节",
		"path": "https://rawcdn.githack.com/quiet324/LiangYouRadioResource201814/se20180406/se/se180406.mp3",
		"id": 19180406
	},
	{
		"time": "20180409",
		"title": "透过性的沟通",
		"downUrl": "http://txly2.net/ly/audio/2018/se/se180409.mp3",
		"duration": 1760,
		"size": "14.1M",
		"artistId": 19,
		"artistName": "恋爱季节",
		"path": "https://rawcdn.githack.com/quiet324/LiangYouRadioResource201815/se20180409/se/se180409.mp3",
		"id": 19180409
	},
	{
		"time": "20180410",
		"title": "学习饶恕（上）",
		"downUrl": "http://txly2.net/ly/audio/2018/se/se180410.mp3",
		"duration": 1760,
		"size": "14.1M",
		"artistId": 19,
		"artistName": "恋爱季节",
		"path": "https://rawcdn.githack.com/quiet324/LiangYouRadioResource201815/se20180410/se/se180410.mp3",
		"id": 19180410
	},
	{
		"time": "20180411",
		"title": "学习饶恕（下）",
		"downUrl": "http://txly2.net/ly/audio/2018/se/se180411.mp3",
		"duration": 1760,
		"size": "14.1M",
		"artistId": 19,
		"artistName": "恋爱季节",
		"path": "https://rawcdn.githack.com/quiet324/LiangYouRadioResource201815/se20180411/se/se180411.mp3",
		"id": 19180411
	},
	{
		"time": "20180412",
		"title": "不贞是如何开始的？",
		"downUrl": "http://txly2.net/ly/audio/2018/se/se180412.mp3",
		"duration": 1760,
		"size": "14.1M",
		"artistId": 19,
		"artistName": "恋爱季节",
		"path": "https://rawcdn.githack.com/quiet324/LiangYouRadioResource201816/se20180412/se/se180412.mp3",
		"id": 19180412
	},
	{
		"time": "20180413",
		"title": "如何使约会内容多采多姿？约会的礼仪；如何扩大生活圈增加接触异性的机会？",
		"downUrl": "http://txly2.net/ly/audio/2018/se/se180413.mp3",
		"duration": 1760,
		"size": "14.1M",
		"artistId": 19,
		"artistName": "恋爱季节",
		"path": "https://rawcdn.githack.com/quiet324/LiangYouRadioResource201816/se20180413/se/se180413.mp3",
		"id": 19180413
	},
	{
		"time": "20180416",
		"title": "不贞的风险有哪些？根本原因是什么？",
		"downUrl": "http://txly2.net/ly/audio/2018/se/se180416.mp3",
		"duration": 1760,
		"size": "14.1M",
		"artistId": 19,
		"artistName": "恋爱季节",
		"path": "https://rawcdn.githack.com/quiet324/LiangYouRadioResource201816/se20180416/se/se180416.mp3",
		"id": 19180416
	},
	{
		"time": "20180417",
		"title": "家庭中角色和责任的确定（上）",
		"downUrl": "http://txly2.net/ly/audio/2018/se/se180417.mp3",
		"duration": 1760,
		"size": "14.1M",
		"artistId": 19,
		"artistName": "恋爱季节",
		"path": "https://rawcdn.githack.com/quiet324/LiangYouRadioResource201816/se20180417/se/se180417.mp3",
		"id": 19180417
	},
	{
		"time": "20180418",
		"title": "家庭中角色和责任的确定（下）",
		"downUrl": "http://txly2.net/ly/audio/2018/se/se180418.mp3",
		"duration": 1760,
		"size": "14.1M",
		"artistId": 19,
		"artistName": "恋爱季节",
		"path": "https://rawcdn.githack.com/quiet324/LiangYouRadioResource201816/se20180418/se/se180418.mp3",
		"id": 19180418
	},
	{
		"time": "20180419",
		"title": "建立成功的合伙关系",
		"downUrl": "http://txly2.net/ly/audio/2018/se/se180419.mp3",
		"duration": 1760,
		"size": "14.1M",
		"artistId": 19,
		"artistName": "恋爱季节",
		"path": "https://rawcdn.githack.com/quiet324/LiangYouRadioResource201816/se20180419/se/se180419.mp3",
		"id": 19180419
	},
	{
		"time": "20180420",
		"title": "幸福家庭的要件是什么？婚姻生活中夫妻两人该如何协调？",
		"downUrl": "http://txly2.net/ly/audio/2018/se/se180420.mp3",
		"duration": 1760,
		"size": "14.1M",
		"artistId": 19,
		"artistName": "恋爱季节",
		"path": "https://rawcdn.githack.com/quiet324/LiangYouRadioResource201816/se20180420/se/se180420.mp3",
		"id": 19180420
	},
	{
		"time": "20180423",
		"title": "生活中的琐碎小事（上）",
		"downUrl": "http://txly2.net/ly/audio/2018/se/se180423.mp3",
		"duration": 1760,
		"size": "14.1M",
		"artistId": 19,
		"artistName": "恋爱季节",
		"path": "https://rawcdn.githack.com/quiet324/LiangYouRadioResource201817/se20180423/se/se180423.mp3",
		"id": 19180423
	},
	{
		"time": "20180424",
		"title": "生活中的琐碎小事（下）",
		"downUrl": "http://txly2.net/ly/audio/2018/se/se180424.mp3",
		"duration": 1760,
		"size": "14.1M",
		"artistId": 19,
		"artistName": "恋爱季节",
		"path": "https://rawcdn.githack.com/quiet324/LiangYouRadioResource201817/se20180424/se/se180424.mp3",
		"id": 19180424
	},
	{
		"time": "20180425",
		"title": "在婚姻中我应该付出多少？",
		"downUrl": "http://txly2.net/ly/audio/2018/se/se180425.mp3",
		"duration": 1760,
		"size": "14.1M",
		"artistId": 19,
		"artistName": "恋爱季节",
		"path": "https://rawcdn.githack.com/quiet324/LiangYouRadioResource201817/se20180425/se/se180425.mp3",
		"id": 19180425
	},
	{
		"time": "20180426",
		"title": "为“配合”彼此的生命，学习适应",
		"downUrl": "http://txly2.net/ly/audio/2018/se/se180426.mp3",
		"duration": 1760,
		"size": "14.1M",
		"artistId": 19,
		"artistName": "恋爱季节",
		"path": "https://rawcdn.githack.com/quiet324/LiangYouRadioResource201817/se20180426/se/se180426.mp3",
		"id": 19180426
	},
	{
		"time": "20180427",
		"title": "面对父母反对自己的交往对象时该怎么办？",
		"downUrl": "http://txly2.net/ly/audio/2018/se/se180427.mp3",
		"duration": 1760,
		"size": "14.1M",
		"artistId": 19,
		"artistName": "恋爱季节",
		"path": "https://rawcdn.githack.com/quiet324/LiangYouRadioResource201817/se20180427/se/se180427.mp3",
		"id": 19180427
	},
	{
		"time": "20180430",
		"title": "夫妻间如何满足彼此的情感需求，以避免婚外情的发生？",
		"downUrl": "http://txly2.net/ly/audio/2018/se/se180430.mp3",
		"duration": 1760,
		"size": "14.1M",
		"artistId": 19,
		"artistName": "恋爱季节",
		"path": "https://rawcdn.githack.com/quiet324/LiangYouRadioResource201818/se20180430/se/se180430.mp3",
		"id": 19180430
	},
	{
		"time": "20180501",
		"title": "什么是爱情银行？",
		"downUrl": "http://txly2.net/ly/audio/2018/se/se180501.mp3",
		"duration": 1760,
		"size": "14.1M",
		"artistId": 19,
		"artistName": "恋爱季节",
		"path": "https://rawcdn.githack.com/quiet324/LiangYouRadioResource201818/se20180501/se/se180501.mp3",
		"id": 19180501
	}
]