[
	{
		"time": "20171030",
		"title": "熬炼精金（1）",
		"downUrl": "http://txly2.net/ly/audio/2017/ug/ug171030.mp3",
		"duration": 1760,
		"size": "14.1M",
		"artistId": 63,
		"artistName": "无尽恩典",
		"path": "https://rawcdn.githack.com/quiet324/LiangYouRadioResource201744/ug20171030/ug/ug171030.mp3",
		"id": 63171030
	},
	{
		"time": "20171031",
		"title": "熬炼精金（2）",
		"downUrl": "http://txly2.net/ly/audio/2017/ug/ug171031.mp3",
		"duration": 1760,
		"size": "14.1M",
		"artistId": 63,
		"artistName": "无尽恩典",
		"path": "https://rawcdn.githack.com/quiet324/LiangYouRadioResource201744/ug20171031/ug/ug171031.mp3",
		"id": 63171031
	},
	{
		"time": "20171101",
		"title": "恩典总是更多（1）",
		"downUrl": "http://txly2.net/ly/audio/2017/ug/ug171101.mp3",
		"duration": 1760,
		"size": "14.1M",
		"artistId": 63,
		"artistName": "无尽恩典",
		"path": "https://rawcdn.githack.com/quiet324/LiangYouRadioResource201744/ug20171101/ug/ug171101.mp3",
		"id": 63171101
	},
	{
		"time": "20171102",
		"title": "恩典总是更多（2）",
		"downUrl": "http://txly2.net/ly/audio/2017/ug/ug171102.mp3",
		"duration": 1760,
		"size": "14.1M",
		"artistId": 63,
		"artistName": "无尽恩典",
		"path": "https://rawcdn.githack.com/quiet324/LiangYouRadioResource201744/ug20171102/ug/ug171102.mp3",
		"id": 63171102
	},
	{
		"time": "20171103",
		"title": "恩典总是更多（3）",
		"downUrl": "http://txly2.net/ly/audio/2017/ug/ug171103.mp3",
		"duration": 1760,
		"size": "14.1M",
		"artistId": 63,
		"artistName": "无尽恩典",
		"path": "https://rawcdn.githack.com/quiet324/LiangYouRadioResource201744/ug20171103/ug/ug171103.mp3",
		"id": 63171103
	},
	{
		"time": "20171106",
		"title": "我是道路、真理和生命（1）",
		"downUrl": "http://txly2.net/ly/audio/2017/ug/ug171106.mp3",
		"duration": 1760,
		"size": "14.1M",
		"artistId": 63,
		"artistName": "无尽恩典",
		"path": "https://rawcdn.githack.com/quiet324/LiangYouRadioResource201745/ug20171106/ug/ug171106.mp3",
		"id": 63171106
	},
	{
		"time": "20171107",
		"title": "我是道路、真理和生命（2）",
		"downUrl": "http://txly2.net/ly/audio/2017/ug/ug171107.mp3",
		"duration": 1760,
		"size": "14.1M",
		"artistId": 63,
		"artistName": "无尽恩典",
		"path": "https://rawcdn.githack.com/quiet324/LiangYouRadioResource201745/ug20171107/ug/ug171107.mp3",
		"id": 63171107
	},
	{
		"time": "20171108",
		"title": "缺失的拼图（1）",
		"downUrl": "http://txly2.net/ly/audio/2017/ug/ug171108.mp3",
		"duration": 1760,
		"size": "14.1M",
		"artistId": 63,
		"artistName": "无尽恩典",
		"path": "https://rawcdn.githack.com/quiet324/LiangYouRadioResource201745/ug20171108/ug/ug171108.mp3",
		"id": 63171108
	},
	{
		"time": "20171109",
		"title": "缺失的拼图（2）",
		"downUrl": "http://txly2.net/ly/audio/2017/ug/ug171109.mp3",
		"duration": 1760,
		"size": "14.1M",
		"artistId": 63,
		"artistName": "无尽恩典",
		"path": "https://rawcdn.githack.com/quiet324/LiangYouRadioResource201745/ug20171109/ug/ug171109.mp3",
		"id": 63171109
	},
	{
		"time": "20171110",
		"title": "恩典总是更多（4）",
		"downUrl": "http://txly2.net/ly/audio/2017/ug/ug171110.mp3",
		"duration": 1760,
		"size": "14.1M",
		"artistId": 63,
		"artistName": "无尽恩典",
		"path": "https://rawcdn.githack.com/quiet324/LiangYouRadioResource201745/ug20171110/ug/ug171110.mp3",
		"id": 63171110
	},
	{
		"time": "20171113",
		"title": "神的气息（1）",
		"downUrl": "http://txly2.net/ly/audio/2017/ug/ug171113.mp3",
		"duration": 1760,
		"size": "14.1M",
		"artistId": 63,
		"artistName": "无尽恩典",
		"path": "https://rawcdn.githack.com/quiet324/LiangYouRadioResource201746/ug20171113/ug/ug171113.mp3",
		"id": 63171113
	},
	{
		"time": "20171114",
		"title": "神的气息（2）",
		"downUrl": "http://txly2.net/ly/audio/2017/ug/ug171114.mp3",
		"duration": 1760,
		"size": "14.1M",
		"artistId": 63,
		"artistName": "无尽恩典",
		"path": "https://rawcdn.githack.com/quiet324/LiangYouRadioResource201746/ug20171114/ug/ug171114.mp3",
		"id": 63171114
	},
	{
		"time": "20171115",
		"title": "神的编织品（1）",
		"downUrl": "http://txly2.net/ly/audio/2017/ug/ug171115.mp3",
		"duration": 1760,
		"size": "14.1M",
		"artistId": 63,
		"artistName": "无尽恩典",
		"path": "https://rawcdn.githack.com/quiet324/LiangYouRadioResource201746/ug20171115/ug/ug171115.mp3",
		"id": 63171115
	},
	{
		"time": "20171116",
		"title": "神的编织品（2）",
		"downUrl": "http://txly2.net/ly/audio/2017/ug/ug171116.mp3",
		"duration": 1760,
		"size": "14.1M",
		"artistId": 63,
		"artistName": "无尽恩典",
		"path": "https://rawcdn.githack.com/quiet324/LiangYouRadioResource201746/ug20171116/ug/ug171116.mp3",
		"id": 63171116
	},
	{
		"time": "20171117",
		"title": "我是谁？我做什么？",
		"downUrl": "http://txly2.net/ly/audio/2017/ug/ug171117.mp3",
		"duration": 1760,
		"size": "14.1M",
		"artistId": 63,
		"artistName": "无尽恩典",
		"path": "https://rawcdn.githack.com/quiet324/LiangYouRadioResource201746/ug20171117/ug/ug171117.mp3",
		"id": 63171117
	},
	{
		"time": "20171120",
		"title": "使人180度掉头的书信（1）",
		"downUrl": "http://txly2.net/ly/audio/2017/ug/ug171120.mp3",
		"duration": 1760,
		"size": "14.1M",
		"artistId": 63,
		"artistName": "无尽恩典",
		"path": "https://rawcdn.githack.com/quiet324/LiangYouRadioResource201747/ug20171120/ug/ug171120.mp3",
		"id": 63171120
	},
	{
		"time": "20171121",
		"title": "使人180度掉头的书信（2）",
		"downUrl": "http://txly2.net/ly/audio/2017/ug/ug171121.mp3",
		"duration": 1760,
		"size": "14.1M",
		"artistId": 63,
		"artistName": "无尽恩典",
		"path": "https://rawcdn.githack.com/quiet324/LiangYouRadioResource201747/ug20171121/ug/ug171121.mp3",
		"id": 63171121
	},
	{
		"time": "20171122",
		"title": "父亲的计划（1）",
		"downUrl": "http://txly2.net/ly/audio/2017/ug/ug171122.mp3",
		"duration": 1760,
		"size": "14.1M",
		"artistId": 63,
		"artistName": "无尽恩典",
		"path": "https://rawcdn.githack.com/quiet324/LiangYouRadioResource201747/ug20171122/ug/ug171122.mp3",
		"id": 63171122
	},
	{
		"time": "20171123",
		"title": "父亲的计划（2）",
		"downUrl": "http://txly2.net/ly/audio/2017/ug/ug171123.mp3",
		"duration": 1760,
		"size": "14.1M",
		"artistId": 63,
		"artistName": "无尽恩典",
		"path": "https://rawcdn.githack.com/quiet324/LiangYouRadioResource201747/ug20171123/ug/ug171123.mp3",
		"id": 63171123
	},
	{
		"time": "20171124",
		"title": "戴上你福音的眼镜",
		"downUrl": "http://txly2.net/ly/audio/2017/ug/ug171124.mp3",
		"duration": 1760,
		"size": "14.1M",
		"artistId": 63,
		"artistName": "无尽恩典",
		"path": "https://rawcdn.githack.com/quiet324/LiangYouRadioResource201747/ug20171124/ug/ug171124.mp3",
		"id": 63171124
	},
	{
		"time": "20171127",
		"title": "儿子的爱（1）",
		"downUrl": "http://txly2.net/ly/audio/2017/ug/ug171127.mp3",
		"duration": 1760,
		"size": "14.1M",
		"artistId": 63,
		"artistName": "无尽恩典",
		"path": "https://rawcdn.githack.com/quiet324/LiangYouRadioResource201748/ug20171127/ug/ug171127.mp3",
		"id": 63171127
	},
	{
		"time": "20171128",
		"title": "儿子的爱（2）",
		"downUrl": "http://txly2.net/ly/audio/2017/ug/ug171128.mp3",
		"duration": 1760,
		"size": "14.1M",
		"artistId": 63,
		"artistName": "无尽恩典",
		"path": "https://rawcdn.githack.com/quiet324/LiangYouRadioResource201748/ug20171128/ug/ug171128.mp3",
		"id": 63171128
	},
	{
		"time": "20171129",
		"title": "圣灵的爱（1）",
		"downUrl": "http://txly2.net/ly/audio/2017/ug/ug171129.mp3",
		"duration": 1760,
		"size": "14.1M",
		"artistId": 63,
		"artistName": "无尽恩典",
		"path": "https://rawcdn.githack.com/quiet324/LiangYouRadioResource201748/ug20171129/ug/ug171129.mp3",
		"id": 63171129
	},
	{
		"time": "20171130",
		"title": "圣灵的爱（2）",
		"downUrl": "http://txly2.net/ly/audio/2017/ug/ug171130.mp3",
		"duration": 1760,
		"size": "14.1M",
		"artistId": 63,
		"artistName": "无尽恩典",
		"path": "https://rawcdn.githack.com/quiet324/LiangYouRadioResource201748/ug20171130/ug/ug171130.mp3",
		"id": 63171130
	},
	{
		"time": "20171201",
		"title": "如何避免经文中的律法主义",
		"downUrl": "http://txly2.net/ly/audio/2017/ug/ug171201.mp3",
		"duration": 1760,
		"size": "14.1M",
		"artistId": 63,
		"artistName": "无尽恩典",
		"path": "https://rawcdn.githack.com/quiet324/LiangYouRadioResource201748/ug20171201/ug/ug171201.mp3",
		"id": 63171201
	},
	{
		"time": "20171204",
		"title": "世界最大的势力（1）",
		"downUrl": "http://txly2.net/ly/audio/2017/ug/ug171204.mp3",
		"duration": 1760,
		"size": "14.1M",
		"artistId": 63,
		"artistName": "无尽恩典",
		"path": "https://rawcdn.githack.com/quiet324/LiangYouRadioResource201749/ug20171204/ug/ug171204.mp3",
		"id": 63171204
	},
	{
		"time": "20171205",
		"title": "世界最大的势力（2）",
		"downUrl": "http://txly2.net/ly/audio/2017/ug/ug171205.mp3",
		"duration": 1760,
		"size": "14.1M",
		"artistId": 63,
		"artistName": "无尽恩典",
		"path": "https://rawcdn.githack.com/quiet324/LiangYouRadioResource201749/ug20171205/ug/ug171205.mp3",
		"id": 63171205
	},
	{
		"time": "20171206",
		"title": "出死入生（1）",
		"downUrl": "http://txly2.net/ly/audio/2017/ug/ug171206.mp3",
		"duration": 1760,
		"size": "14.1M",
		"artistId": 63,
		"artistName": "无尽恩典",
		"path": "https://rawcdn.githack.com/quiet324/LiangYouRadioResource201749/ug20171206/ug/ug171206.mp3",
		"id": 63171206
	},
	{
		"time": "20171207",
		"title": "出死入生（2）",
		"downUrl": "http://txly2.net/ly/audio/2017/ug/ug171207.mp3",
		"duration": 1760,
		"size": "14.1M",
		"artistId": 63,
		"artistName": "无尽恩典",
		"path": "https://rawcdn.githack.com/quiet324/LiangYouRadioResource201749/ug20171207/ug/ug171207.mp3",
		"id": 63171207
	},
	{
		"time": "20171208",
		"title": "为什么我们还会犯罪",
		"downUrl": "http://txly2.net/ly/audio/2017/ug/ug171208.mp3",
		"duration": 1760,
		"size": "14.1M",
		"artistId": 63,
		"artistName": "无尽恩典",
		"path": "https://rawcdn.githack.com/quiet324/LiangYouRadioResource201749/ug20171208/ug/ug171208.mp3",
		"id": 63171208
	},
	{
		"time": "20171211",
		"title": "你是神的杰作",
		"downUrl": "http://txly2.net/ly/audio/2017/ug/ug171211.mp3",
		"duration": 1760,
		"size": "14.1M",
		"artistId": 63,
		"artistName": "无尽恩典",
		"path": "https://rawcdn.githack.com/quiet324/LiangYouRadioResource201750/ug20171211/ug/ug171211.mp3",
		"id": 63171211
	},
	{
		"time": "20171212",
		"title": "当墙倒塌的时候（1）",
		"downUrl": "http://txly2.net/ly/audio/2017/ug/ug171212.mp3",
		"duration": 1760,
		"size": "14.1M",
		"artistId": 63,
		"artistName": "无尽恩典",
		"path": "https://rawcdn.githack.com/quiet324/LiangYouRadioResource201750/ug20171212/ug/ug171212.mp3",
		"id": 63171212
	},
	{
		"time": "20171213",
		"title": "当墙倒塌的时候（2）",
		"downUrl": "http://txly2.net/ly/audio/2017/ug/ug171213.mp3",
		"duration": 1760,
		"size": "14.1M",
		"artistId": 63,
		"artistName": "无尽恩典",
		"path": "https://rawcdn.githack.com/quiet324/LiangYouRadioResource201750/ug20171213/ug/ug171213.mp3",
		"id": 63171213
	},
	{
		"time": "20171214",
		"title": "靠主建造（1）",
		"downUrl": "http://txly2.net/ly/audio/2017/ug/ug171214.mp3",
		"duration": 1760,
		"size": "14.1M",
		"artistId": 63,
		"artistName": "无尽恩典",
		"path": "https://rawcdn.githack.com/quiet324/LiangYouRadioResource201750/ug20171214/ug/ug171214.mp3",
		"id": 63171214
	},
	{
		"time": "20171215",
		"title": "靠主建造（2）",
		"downUrl": "http://txly2.net/ly/audio/2017/ug/ug171215.mp3",
		"duration": 1760,
		"size": "14.1M",
		"artistId": 63,
		"artistName": "无尽恩典",
		"path": "https://rawcdn.githack.com/quiet324/LiangYouRadioResource201750/ug20171215/ug/ug171215.mp3",
		"id": 63171215
	},
	{
		"time": "20171218",
		"title": "靠主建造（3）",
		"downUrl": "http://txly2.net/ly/audio/2017/ug/ug171218.mp3",
		"duration": 1760,
		"size": "14.1M",
		"artistId": 63,
		"artistName": "无尽恩典",
		"path": "https://rawcdn.githack.com/quiet324/LiangYouRadioResource201751/ug20171218/ug/ug171218.mp3",
		"id": 63171218
	},
	{
		"time": "20171219",
		"title": "荣耀的捆绑（1）",
		"downUrl": "http://txly2.net/ly/audio/2017/ug/ug171219.mp3",
		"duration": 1760,
		"size": "14.1M",
		"artistId": 63,
		"artistName": "无尽恩典",
		"path": "https://rawcdn.githack.com/quiet324/LiangYouRadioResource201751/ug20171219/ug/ug171219.mp3",
		"id": 63171219
	},
	{
		"time": "20171220",
		"title": "荣耀的捆绑（2）",
		"downUrl": "http://txly2.net/ly/audio/2017/ug/ug171220.mp3",
		"duration": 1760,
		"size": "14.1M",
		"artistId": 63,
		"artistName": "无尽恩典",
		"path": "https://rawcdn.githack.com/quiet324/LiangYouRadioResource201751/ug20171220/ug/ug171220.mp3",
		"id": 63171220
	},
	{
		"time": "20171221",
		"title": "爱主更多（1）",
		"downUrl": "http://txly2.net/ly/audio/2017/ug/ug171221.mp3",
		"duration": 1760,
		"size": "14.1M",
		"artistId": 63,
		"artistName": "无尽恩典",
		"path": "https://rawcdn.githack.com/quiet324/LiangYouRadioResource201751/ug20171221/ug/ug171221.mp3",
		"id": 63171221
	},
	{
		"time": "20171222",
		"title": "爱主更多（2）",
		"downUrl": "http://txly2.net/ly/audio/2017/ug/ug171222.mp3",
		"duration": 1760,
		"size": "14.1M",
		"artistId": 63,
		"artistName": "无尽恩典",
		"path": "https://rawcdn.githack.com/quiet324/LiangYouRadioResource201751/ug20171222/ug/ug171222.mp3",
		"id": 63171222
	},
	{
		"time": "20171225",
		"title": "超越疑虑和梦想（1）",
		"downUrl": "http://txly2.net/ly/audio/2017/ug/ug171225.mp3",
		"duration": 1760,
		"size": "14.1M",
		"artistId": 63,
		"artistName": "无尽恩典",
		"path": "https://rawcdn.githack.com/quiet324/LiangYouRadioResource201752/ug20171225/ug/ug171225.mp3",
		"id": 63171225
	},
	{
		"time": "20171226",
		"title": "超越疑虑和梦想（2）",
		"downUrl": "http://txly2.net/ly/audio/2017/ug/ug171226.mp3",
		"duration": 1760,
		"size": "14.1M",
		"artistId": 63,
		"artistName": "无尽恩典",
		"path": "https://rawcdn.githack.com/quiet324/LiangYouRadioResource201752/ug20171226/ug/ug171226.mp3",
		"id": 63171226
	},
	{
		"time": "20171227",
		"title": "树枝上的铁丝（1）",
		"downUrl": "http://txly2.net/ly/audio/2017/ug/ug171227.mp3",
		"duration": 1760,
		"size": "14.1M",
		"artistId": 63,
		"artistName": "无尽恩典",
		"path": "https://rawcdn.githack.com/quiet324/LiangYouRadioResource201752/ug20171227/ug/ug171227.mp3",
		"id": 63171227
	},
	{
		"time": "20171228",
		"title": "树枝上的铁丝（2）",
		"downUrl": "http://txly2.net/ly/audio/2017/ug/ug171228.mp3",
		"duration": 1760,
		"size": "14.1M",
		"artistId": 63,
		"artistName": "无尽恩典",
		"path": "https://rawcdn.githack.com/quiet324/LiangYouRadioResource201752/ug20171228/ug/ug171228.mp3",
		"id": 63171228
	},
	{
		"time": "20171229",
		"title": "耶诞节的摩西（1）",
		"downUrl": "http://txly2.net/ly/audio/2017/ug/ug171229.mp3",
		"duration": 1760,
		"size": "14.1M",
		"artistId": 63,
		"artistName": "无尽恩典",
		"path": "https://rawcdn.githack.com/quiet324/LiangYouRadioResource201752/ug20171229/ug/ug171229.mp3",
		"id": 63171229
	},
	{
		"time": "20180101",
		"title": "耶诞节的摩西（2）",
		"downUrl": "http://txly2.net/ly/audio/2018/ug/ug180101.mp3",
		"duration": 1760,
		"size": "14.1M",
		"artistId": 63,
		"artistName": "无尽恩典",
		"path": "https://rawcdn.githack.com/quiet324/LiangYouRadioResource201801/ug20180101/ug/ug180101.mp3",
		"id": 63180101
	},
	{
		"time": "20180102",
		"title": "圣诞节的悔疚（1）",
		"downUrl": "http://txly2.net/ly/audio/2018/ug/ug180102.mp3",
		"duration": 1760,
		"size": "14.1M",
		"artistId": 63,
		"artistName": "无尽恩典",
		"path": "https://rawcdn.githack.com/quiet324/LiangYouRadioResource201801/ug20180102/ug/ug180102.mp3",
		"id": 63180102
	},
	{
		"time": "20180103",
		"title": "圣诞节的悔疚（2）",
		"downUrl": "http://txly2.net/ly/audio/2018/ug/ug180103.mp3",
		"duration": 1760,
		"size": "14.1M",
		"artistId": 63,
		"artistName": "无尽恩典",
		"path": "https://rawcdn.githack.com/quiet324/LiangYouRadioResource201801/ug20180103/ug/ug180103.mp3",
		"id": 63180103
	},
	{
		"time": "20180104",
		"title": "圣诞小城（1）",
		"downUrl": "http://txly2.net/ly/audio/2018/ug/ug180104.mp3",
		"duration": 1760,
		"size": "14.1M",
		"artistId": 63,
		"artistName": "无尽恩典",
		"path": "https://rawcdn.githack.com/quiet324/LiangYouRadioResource201801/ug20180104/ug/ug180104.mp3",
		"id": 63180104
	},
	{
		"time": "20180105",
		"title": "圣诞小城（2）",
		"downUrl": "http://txly2.net/ly/audio/2018/ug/ug180105.mp3",
		"duration": 1760,
		"size": "14.1M",
		"artistId": 63,
		"artistName": "无尽恩典",
		"path": "https://rawcdn.githack.com/quiet324/LiangYouRadioResource201801/ug20180105/ug/ug180105.mp3",
		"id": 63180105
	},
	{
		"time": "20180108",
		"title": "最恶劣的圣诞节故事（1）",
		"downUrl": "http://txly2.net/ly/audio/2018/ug/ug180108.mp3",
		"duration": 1760,
		"size": "14.1M",
		"artistId": 63,
		"artistName": "无尽恩典",
		"path": "https://rawcdn.githack.com/quiet324/LiangYouRadioResource201802/ug20180108/ug/ug180108.mp3",
		"id": 63180108
	},
	{
		"time": "20180109",
		"title": "最恶劣的圣诞节故事（2）",
		"downUrl": "http://txly2.net/ly/audio/2018/ug/ug180109.mp3",
		"duration": 1760,
		"size": "14.1M",
		"artistId": 63,
		"artistName": "无尽恩典",
		"path": "https://rawcdn.githack.com/quiet324/LiangYouRadioResource201802/ug20180109/ug/ug180109.mp3",
		"id": 63180109
	},
	{
		"time": "20180110",
		"title": "以马内利在商场",
		"downUrl": "http://txly2.net/ly/audio/2018/ug/ug180110.mp3",
		"duration": 1760,
		"size": "14.1M",
		"artistId": 63,
		"artistName": "无尽恩典",
		"path": "https://rawcdn.githack.com/quiet324/LiangYouRadioResource201802/ug20180110/ug/ug180110.mp3",
		"id": 63180110
	},
	{
		"time": "20180111",
		"title": "我孤独逃脱是为了告诉你（1）",
		"downUrl": "http://txly2.net/ly/audio/2018/ug/ug180111.mp3",
		"duration": 1760,
		"size": "14.1M",
		"artistId": 63,
		"artistName": "无尽恩典",
		"path": "https://rawcdn.githack.com/quiet324/LiangYouRadioResource201802/ug20180111/ug/ug180111.mp3",
		"id": 63180111
	},
	{
		"time": "20180112",
		"title": "我孤独逃脱是为了告诉你（2）",
		"downUrl": "http://txly2.net/ly/audio/2018/ug/ug180112.mp3",
		"duration": 1760,
		"size": "14.1M",
		"artistId": 63,
		"artistName": "无尽恩典",
		"path": "https://rawcdn.githack.com/quiet324/LiangYouRadioResource201802/ug20180112/ug/ug180112.mp3",
		"id": 63180112
	},
	{
		"time": "20180115",
		"title": "我是生命的粮（1）",
		"downUrl": "http://txly2.net/ly/audio/2018/ug/ug180115.mp3",
		"duration": 1760,
		"size": "14.1M",
		"artistId": 63,
		"artistName": "无尽恩典",
		"path": "https://rawcdn.githack.com/quiet324/LiangYouRadioResource201803/ug20180115/ug/ug180115.mp3",
		"id": 63180115
	},
	{
		"time": "20180116",
		"title": "我是生命的粮（2）",
		"downUrl": "http://txly2.net/ly/audio/2018/ug/ug180116.mp3",
		"duration": 1760,
		"size": "14.1M",
		"artistId": 63,
		"artistName": "无尽恩典",
		"path": "https://rawcdn.githack.com/quiet324/LiangYouRadioResource201803/ug20180116/ug/ug180116.mp3",
		"id": 63180116
	},
	{
		"time": "20180117",
		"title": "我是世界的光（1）",
		"downUrl": "http://txly2.net/ly/audio/2018/ug/ug180117.mp3",
		"duration": 1760,
		"size": "14.1M",
		"artistId": 63,
		"artistName": "无尽恩典",
		"path": "https://rawcdn.githack.com/quiet324/LiangYouRadioResource201803/ug20180117/ug/ug180117.mp3",
		"id": 63180117
	},
	{
		"time": "20180118",
		"title": "我是世界的光（2）",
		"downUrl": "http://txly2.net/ly/audio/2018/ug/ug180118.mp3",
		"duration": 1760,
		"size": "14.1M",
		"artistId": 63,
		"artistName": "无尽恩典",
		"path": "https://rawcdn.githack.com/quiet324/LiangYouRadioResource201803/ug20180118/ug/ug180118.mp3",
		"id": 63180118
	},
	{
		"time": "20180119",
		"title": "我是好牧人（1）",
		"downUrl": "http://txly2.net/ly/audio/2018/ug/ug180119.mp3",
		"duration": 1760,
		"size": "14.1M",
		"artistId": 63,
		"artistName": "无尽恩典",
		"path": "https://rawcdn.githack.com/quiet324/LiangYouRadioResource201803/ug20180119/ug/ug180119.mp3",
		"id": 63180119
	},
	{
		"time": "20180122",
		"title": "我是好牧人（2）",
		"downUrl": "http://txly2.net/ly/audio/2018/ug/ug180122.mp3",
		"duration": 1760,
		"size": "14.1M",
		"artistId": 63,
		"artistName": "无尽恩典",
		"path": "https://rawcdn.githack.com/quiet324/LiangYouRadioResource201804/ug20180122/ug/ug180122.mp3",
		"id": 63180122
	},
	{
		"time": "20180123",
		"title": "相同的呼召，不同的恩赐（1）",
		"downUrl": "http://txly2.net/ly/audio/2018/ug/ug180123.mp3",
		"duration": 1760,
		"size": "14.1M",
		"artistId": 63,
		"artistName": "无尽恩典",
		"path": "https://rawcdn.githack.com/quiet324/LiangYouRadioResource201804/ug20180123/ug/ug180123.mp3",
		"id": 63180123
	},
	{
		"time": "20180124",
		"title": "相同的呼召，不同的恩赐（2）",
		"downUrl": "http://txly2.net/ly/audio/2018/ug/ug180124.mp3",
		"duration": 1760,
		"size": "14.1M",
		"artistId": 63,
		"artistName": "无尽恩典",
		"path": "https://rawcdn.githack.com/quiet324/LiangYouRadioResource201804/ug20180124/ug/ug180124.mp3",
		"id": 63180124
	},
	{
		"time": "20180125",
		"title": "蜥蜴和天马的启示（1）",
		"downUrl": "http://txly2.net/ly/audio/2018/ug/ug180125.mp3",
		"duration": 1760,
		"size": "14.1M",
		"artistId": 63,
		"artistName": "无尽恩典",
		"path": "https://rawcdn.githack.com/quiet324/LiangYouRadioResource201804/ug20180125/ug/ug180125.mp3",
		"id": 63180125
	},
	{
		"time": "20180126",
		"title": "蜥蜴和天马的启示（2）",
		"downUrl": "http://txly2.net/ly/audio/2018/ug/ug180126.mp3",
		"duration": 1760,
		"size": "14.1M",
		"artistId": 63,
		"artistName": "无尽恩典",
		"path": "https://rawcdn.githack.com/quiet324/LiangYouRadioResource201804/ug20180126/ug/ug180126.mp3",
		"id": 63180126
	},
	{
		"time": "20180129",
		"title": "恩典的见证（1）",
		"downUrl": "http://txly2.net/ly/audio/2018/ug/ug180129.mp3",
		"duration": 1760,
		"size": "14.1M",
		"artistId": 63,
		"artistName": "无尽恩典",
		"path": "https://rawcdn.githack.com/quiet324/LiangYouRadioResource201805/ug20180129/ug/ug180129.mp3",
		"id": 63180129
	},
	{
		"time": "20180130",
		"title": "恩典的见证（2）",
		"downUrl": "http://txly2.net/ly/audio/2018/ug/ug180130.mp3",
		"duration": 1760,
		"size": "14.1M",
		"artistId": 63,
		"artistName": "无尽恩典",
		"path": "https://rawcdn.githack.com/quiet324/LiangYouRadioResource201805/ug20180130/ug/ug180130.mp3",
		"id": 63180130
	},
	{
		"time": "20180131",
		"title": "工作（1）",
		"downUrl": "http://txly2.net/ly/audio/2018/ug/ug180131.mp3",
		"duration": 1760,
		"size": "14.1M",
		"artistId": 63,
		"artistName": "无尽恩典",
		"path": "https://rawcdn.githack.com/quiet324/LiangYouRadioResource201805/ug20180131/ug/ug180131.mp3",
		"id": 63180131
	},
	{
		"time": "20180201",
		"title": "工作（2）",
		"downUrl": "http://txly2.net/ly/audio/2018/ug/ug180201.mp3",
		"duration": 1760,
		"size": "14.1M",
		"artistId": 63,
		"artistName": "无尽恩典",
		"path": "https://rawcdn.githack.com/quiet324/LiangYouRadioResource201805/ug20180201/ug/ug180201.mp3",
		"id": 63180201
	},
	{
		"time": "20180202",
		"title": "信心的盔甲（1）",
		"downUrl": "http://txly2.net/ly/audio/2018/ug/ug180202.mp3",
		"duration": 1760,
		"size": "14.1M",
		"artistId": 63,
		"artistName": "无尽恩典",
		"path": "https://rawcdn.githack.com/quiet324/LiangYouRadioResource201805/ug20180202/ug/ug180202.mp3",
		"id": 63180202
	},
	{
		"time": "20180205",
		"title": "信心的盔甲（2）",
		"downUrl": "http://txly2.net/ly/audio/2018/ug/ug180205.mp3",
		"duration": 1760,
		"size": "14.1M",
		"artistId": 63,
		"artistName": "无尽恩典",
		"path": "https://rawcdn.githack.com/quiet324/LiangYouRadioResource201806/ug20180205/ug/ug180205.mp3",
		"id": 63180205
	},
	{
		"time": "20180206",
		"title": "站立得稳（1）",
		"downUrl": "http://txly2.net/ly/audio/2018/ug/ug180206.mp3",
		"duration": 1760,
		"size": "14.1M",
		"artistId": 63,
		"artistName": "无尽恩典",
		"path": "https://rawcdn.githack.com/quiet324/LiangYouRadioResource201806/ug20180206/ug/ug180206.mp3",
		"id": 63180206
	},
	{
		"time": "20180207",
		"title": "站立得稳（2）",
		"downUrl": "http://txly2.net/ly/audio/2018/ug/ug180207.mp3",
		"duration": 1760,
		"size": "14.1M",
		"artistId": 63,
		"artistName": "无尽恩典",
		"path": "https://rawcdn.githack.com/quiet324/LiangYouRadioResource201806/ug20180207/ug/ug180207.mp3",
		"id": 63180207
	},
	{
		"time": "20180208",
		"title": "当人生跌入绝境的时候（1）",
		"downUrl": "http://txly2.net/ly/audio/2018/ug/ug180208.mp3",
		"duration": 1760,
		"size": "14.1M",
		"artistId": 63,
		"artistName": "无尽恩典",
		"path": "https://rawcdn.githack.com/quiet324/LiangYouRadioResource201806/ug20180208/ug/ug180208.mp3",
		"id": 63180208
	},
	{
		"time": "20180209",
		"title": "当人生跌入绝境的时候（2）",
		"downUrl": "http://txly2.net/ly/audio/2018/ug/ug180209.mp3",
		"duration": 1760,
		"size": "14.1M",
		"artistId": 63,
		"artistName": "无尽恩典",
		"path": "https://rawcdn.githack.com/quiet324/LiangYouRadioResource201806/ug20180209/ug/ug180209.mp3",
		"id": 63180209
	},
	{
		"time": "20180209",
		"title": "当人生跌入绝境的时候（2）",
		"downUrl": "http://txly2.net/ly/audio/2018/ug/ug180209.mp3",
		"duration": 1760,
		"size": "14.1M",
		"artistId": 63,
		"artistName": "无尽恩典",
		"path": "https://rawcdn.githack.com/quiet324/LiangYouRadioResource201807/ug20180209/ug/ug180209.mp3",
		"id": 63180209
	},
	{
		"time": "20180216",
		"title": "反映他的光（3）",
		"downUrl": "http://txly2.net/ly/audio/2018/ug/ug180216.mp3",
		"duration": 1760,
		"size": "14.1M",
		"artistId": 63,
		"artistName": "无尽恩典",
		"path": "https://rawcdn.githack.com/quiet324/LiangYouRadioResource201807/ug20180216/ug/ug180216.mp3",
		"id": 63180216
	},
	{
		"time": "20180215",
		"title": "反映他的光（2）",
		"downUrl": "http://txly2.net/ly/audio/2018/ug/ug180215.mp3",
		"duration": 1760,
		"size": "14.1M",
		"artistId": 63,
		"artistName": "无尽恩典",
		"path": "https://rawcdn.githack.com/quiet324/LiangYouRadioResource201807/ug20180215/ug/ug180215.mp3",
		"id": 63180215
	},
	{
		"time": "20180214",
		"title": "反映他的光（1）",
		"downUrl": "http://txly2.net/ly/audio/2018/ug/ug180214.mp3",
		"duration": 1760,
		"size": "14.1M",
		"artistId": 63,
		"artistName": "无尽恩典",
		"path": "https://rawcdn.githack.com/quiet324/LiangYouRadioResource201807/ug20180214/ug/ug180214.mp3",
		"id": 63180214
	},
	{
		"time": "20180213",
		"title": "耶稣的味道（2）",
		"downUrl": "http://txly2.net/ly/audio/2018/ug/ug180213.mp3",
		"duration": 1760,
		"size": "14.1M",
		"artistId": 63,
		"artistName": "无尽恩典",
		"path": "https://rawcdn.githack.com/quiet324/LiangYouRadioResource201807/ug20180213/ug/ug180213.mp3",
		"id": 63180213
	},
	{
		"time": "20180212",
		"title": "耶稣的味道（1）",
		"downUrl": "http://txly2.net/ly/audio/2018/ug/ug180212.mp3",
		"duration": 1760,
		"size": "14.1M",
		"artistId": 63,
		"artistName": "无尽恩典",
		"path": "https://rawcdn.githack.com/quiet324/LiangYouRadioResource201807/ug20180212/ug/ug180212.mp3",
		"id": 63180212
	},
	{
		"time": "20180219",
		"title": "真正的山羊诅咒（1）",
		"downUrl": "http://txly2.net/ly/audio/2018/ug/ug180219.mp3",
		"duration": 1760,
		"size": "14.1M",
		"artistId": 63,
		"artistName": "无尽恩典",
		"path": "https://rawcdn.githack.com/quiet324/LiangYouRadioResource201808/ug20180219/ug/ug180219.mp3",
		"id": 63180219
	},
	{
		"time": "20180220",
		"title": "真正的山羊诅咒（2）",
		"downUrl": "http://txly2.net/ly/audio/2018/ug/ug180220.mp3",
		"duration": 1760,
		"size": "14.1M",
		"artistId": 63,
		"artistName": "无尽恩典",
		"path": "https://rawcdn.githack.com/quiet324/LiangYouRadioResource201808/ug20180220/ug/ug180220.mp3",
		"id": 63180220
	},
	{
		"time": "20180221",
		"title": "称义和成圣",
		"downUrl": "http://txly2.net/ly/audio/2018/ug/ug180221.mp3",
		"duration": 1760,
		"size": "14.1M",
		"artistId": 63,
		"artistName": "无尽恩典",
		"path": "https://rawcdn.githack.com/quiet324/LiangYouRadioResource201808/ug20180221/ug/ug180221.mp3",
		"id": 63180221
	},
	{
		"time": "20180222",
		"title": "不全是关乎我的事（1）",
		"downUrl": "http://txly2.net/ly/audio/2018/ug/ug180222.mp3",
		"duration": 1760,
		"size": "14.1M",
		"artistId": 63,
		"artistName": "无尽恩典",
		"path": "https://rawcdn.githack.com/quiet324/LiangYouRadioResource201808/ug20180222/ug/ug180222.mp3",
		"id": 63180222
	},
	{
		"time": "20180223",
		"title": "不全是关乎我的事（2）",
		"downUrl": "http://txly2.net/ly/audio/2018/ug/ug180223.mp3",
		"duration": 1760,
		"size": "14.1M",
		"artistId": 63,
		"artistName": "无尽恩典",
		"path": "https://rawcdn.githack.com/quiet324/LiangYouRadioResource201808/ug20180223/ug/ug180223.mp3",
		"id": 63180223
	},
	{
		"time": "20180302",
		"title": "迈向将来（2）",
		"downUrl": "http://txly2.net/ly/audio/2018/ug/ug180302.mp3",
		"duration": 1760,
		"size": "14.1M",
		"artistId": 63,
		"artistName": "无尽恩典",
		"path": "https://rawcdn.githack.com/quiet324/LiangYouRadioResource201810/ug20180302/ug/ug180302.mp3",
		"id": 63180302
	},
	{
		"time": "20180301",
		"title": "迈向将来（1）",
		"downUrl": "http://txly2.net/ly/audio/2018/ug/ug180301.mp3",
		"duration": 1760,
		"size": "14.1M",
		"artistId": 63,
		"artistName": "无尽恩典",
		"path": "https://rawcdn.githack.com/quiet324/LiangYouRadioResource201810/ug20180301/ug/ug180301.mp3",
		"id": 63180301
	},
	{
		"time": "20180228",
		"title": "祷告问与答",
		"downUrl": "http://txly2.net/ly/audio/2018/ug/ug180228.mp3",
		"duration": 1760,
		"size": "14.1M",
		"artistId": 63,
		"artistName": "无尽恩典",
		"path": "https://rawcdn.githack.com/quiet324/LiangYouRadioResource201810/ug20180228/ug/ug180228.mp3",
		"id": 63180228
	},
	{
		"time": "20180227",
		"title": "福音的触摸（2）",
		"downUrl": "http://txly2.net/ly/audio/2018/ug/ug180227.mp3",
		"duration": 1760,
		"size": "14.1M",
		"artistId": 63,
		"artistName": "无尽恩典",
		"path": "https://rawcdn.githack.com/quiet324/LiangYouRadioResource201810/ug20180227/ug/ug180227.mp3",
		"id": 63180227
	},
	{
		"time": "20180226",
		"title": "福音的触摸（1）",
		"downUrl": "http://txly2.net/ly/audio/2018/ug/ug180226.mp3",
		"duration": 1760,
		"size": "14.1M",
		"artistId": 63,
		"artistName": "无尽恩典",
		"path": "https://rawcdn.githack.com/quiet324/LiangYouRadioResource201810/ug20180226/ug/ug180226.mp3",
		"id": 63180226
	},
	{
		"time": "20180305",
		"title": "即或不然（1）",
		"downUrl": "http://txly2.net/ly/audio/2018/ug/ug180305.mp3",
		"duration": 1760,
		"size": "14.1M",
		"artistId": 63,
		"artistName": "无尽恩典",
		"path": "https://rawcdn.githack.com/quiet324/LiangYouRadioResource201810/ug20180305/ug/ug180305.mp3",
		"id": 63180305
	},
	{
		"time": "20180306",
		"title": "即或不然（2）",
		"downUrl": "http://txly2.net/ly/audio/2018/ug/ug180306.mp3",
		"duration": 1760,
		"size": "14.1M",
		"artistId": 63,
		"artistName": "无尽恩典",
		"path": "https://rawcdn.githack.com/quiet324/LiangYouRadioResource201810/ug20180306/ug/ug180306.mp3",
		"id": 63180306
	},
	{
		"time": "20180307",
		"title": "羔羊的信心（1）",
		"downUrl": "http://txly2.net/ly/audio/2018/ug/ug180307.mp3",
		"duration": 1760,
		"size": "14.1M",
		"artistId": 63,
		"artistName": "无尽恩典",
		"path": "https://rawcdn.githack.com/quiet324/LiangYouRadioResource201810/ug20180307/ug/ug180307.mp3",
		"id": 63180307
	},
	{
		"time": "20180308",
		"title": "羔羊的信心（2）",
		"downUrl": "http://txly2.net/ly/audio/2018/ug/ug180308.mp3",
		"duration": 1760,
		"size": "14.1M",
		"artistId": 63,
		"artistName": "无尽恩典",
		"path": "https://rawcdn.githack.com/quiet324/LiangYouRadioResource201810/ug20180308/ug/ug180308.mp3",
		"id": 63180308
	},
	{
		"time": "20180309",
		"title": "夫妻的角色",
		"downUrl": "http://txly2.net/ly/audio/2018/ug/ug180309.mp3",
		"duration": 1760,
		"size": "14.1M",
		"artistId": 63,
		"artistName": "无尽恩典",
		"path": "https://rawcdn.githack.com/quiet324/LiangYouRadioResource201810/ug20180309/ug/ug180309.mp3",
		"id": 63180309
	},
	{
		"time": "20180312",
		"title": "警示的爱（1）",
		"downUrl": "http://txly2.net/ly/audio/2018/ug/ug180312.mp3",
		"duration": 1760,
		"size": "14.1M",
		"artistId": 63,
		"artistName": "无尽恩典",
		"path": "https://rawcdn.githack.com/quiet324/LiangYouRadioResource201811/ug20180312/ug/ug180312.mp3",
		"id": 63180312
	},
	{
		"time": "20180313",
		"title": "警示的爱（2）",
		"downUrl": "http://txly2.net/ly/audio/2018/ug/ug180313.mp3",
		"duration": 1760,
		"size": "14.1M",
		"artistId": 63,
		"artistName": "无尽恩典",
		"path": "https://rawcdn.githack.com/quiet324/LiangYouRadioResource201811/ug20180313/ug/ug180313.mp3",
		"id": 63180313
	},
	{
		"time": "20180314",
		"title": "狮子洞中的人生（1）",
		"downUrl": "http://txly2.net/ly/audio/2018/ug/ug180314.mp3",
		"duration": 1760,
		"size": "14.1M",
		"artistId": 63,
		"artistName": "无尽恩典",
		"path": "https://rawcdn.githack.com/quiet324/LiangYouRadioResource201811/ug20180314/ug/ug180314.mp3",
		"id": 63180314
	},
	{
		"time": "20180315",
		"title": "狮子洞中的人生（2）",
		"downUrl": "http://txly2.net/ly/audio/2018/ug/ug180315.mp3",
		"duration": 1760,
		"size": "14.1M",
		"artistId": 63,
		"artistName": "无尽恩典",
		"path": "https://rawcdn.githack.com/quiet324/LiangYouRadioResource201811/ug20180315/ug/ug180315.mp3",
		"id": 63180315
	},
	{
		"time": "20180316",
		"title": "如果我继续犯罪会怎么样？",
		"downUrl": "http://txly2.net/ly/audio/2018/ug/ug180316.mp3",
		"duration": 1760,
		"size": "14.1M",
		"artistId": 63,
		"artistName": "无尽恩典",
		"path": "https://rawcdn.githack.com/quiet324/LiangYouRadioResource201811/ug20180316/ug/ug180316.mp3",
		"id": 63180316
	},
	{
		"time": "20180319",
		"title": "宝座的奥秘与得胜（1）",
		"downUrl": "http://txly2.net/ly/audio/2018/ug/ug180319.mp3",
		"duration": 1760,
		"size": "14.1M",
		"artistId": 63,
		"artistName": "无尽恩典",
		"path": "https://rawcdn.githack.com/quiet324/LiangYouRadioResource201813/ug20180319/ug/ug180319.mp3",
		"id": 63180319
	},
	{
		"time": "20180320",
		"title": "宝座的奥秘与得胜（2）",
		"downUrl": "http://txly2.net/ly/audio/2018/ug/ug180320.mp3",
		"duration": 1760,
		"size": "14.1M",
		"artistId": 63,
		"artistName": "无尽恩典",
		"path": "https://rawcdn.githack.com/quiet324/LiangYouRadioResource201813/ug20180320/ug/ug180320.mp3",
		"id": 63180320
	},
	{
		"time": "20180321",
		"title": "牺牲的头（1）",
		"downUrl": "http://txly2.net/ly/audio/2018/ug/ug180321.mp3",
		"duration": 1760,
		"size": "14.1M",
		"artistId": 63,
		"artistName": "无尽恩典",
		"path": "https://rawcdn.githack.com/quiet324/LiangYouRadioResource201813/ug20180321/ug/ug180321.mp3",
		"id": 63180321
	},
	{
		"time": "20180322",
		"title": "牺牲的头（2）",
		"downUrl": "http://txly2.net/ly/audio/2018/ug/ug180322.mp3",
		"duration": 1760,
		"size": "14.1M",
		"artistId": 63,
		"artistName": "无尽恩典",
		"path": "https://rawcdn.githack.com/quiet324/LiangYouRadioResource201813/ug20180322/ug/ug180322.mp3",
		"id": 63180322
	},
	{
		"time": "20180323",
		"title": "妻子的智慧",
		"downUrl": "http://txly2.net/ly/audio/2018/ug/ug180323.mp3",
		"duration": 1760,
		"size": "14.1M",
		"artistId": 63,
		"artistName": "无尽恩典",
		"path": "https://rawcdn.githack.com/quiet324/LiangYouRadioResource201813/ug20180323/ug/ug180323.mp3",
		"id": 63180323
	},
	{
		"time": "20180326",
		"title": "教养孩子的模式（1）",
		"downUrl": "http://txly2.net/ly/audio/2018/ug/ug180326.mp3",
		"duration": 1760,
		"size": "14.1M",
		"artistId": 63,
		"artistName": "无尽恩典",
		"path": "https://rawcdn.githack.com/quiet324/LiangYouRadioResource201813/ug20180326/ug/ug180326.mp3",
		"id": 63180326
	},
	{
		"time": "20180327",
		"title": "教养孩子的模式（2）",
		"downUrl": "http://txly2.net/ly/audio/2018/ug/ug180327.mp3",
		"duration": 1760,
		"size": "14.1M",
		"artistId": 63,
		"artistName": "无尽恩典",
		"path": "https://rawcdn.githack.com/quiet324/LiangYouRadioResource201813/ug20180327/ug/ug180327.mp3",
		"id": 63180327
	},
	{
		"time": "20180328",
		"title": "迈向将来",
		"downUrl": "http://txly2.net/ly/audio/2018/ug/ug180328.mp3",
		"duration": 1760,
		"size": "14.1M",
		"artistId": 63,
		"artistName": "无尽恩典",
		"path": "https://rawcdn.githack.com/quiet324/LiangYouRadioResource201813/ug20180328/ug/ug180328.mp3",
		"id": 63180328
	},
	{
		"time": "20180329",
		"title": "不是终结（1）",
		"downUrl": "http://txly2.net/ly/audio/2018/ug/ug180329.mp3",
		"duration": 1760,
		"size": "14.1M",
		"artistId": 63,
		"artistName": "无尽恩典",
		"path": "https://rawcdn.githack.com/quiet324/LiangYouRadioResource201813/ug20180329/ug/ug180329.mp3",
		"id": 63180329
	},
	{
		"time": "20180330",
		"title": "不是终结（2）",
		"downUrl": "http://txly2.net/ly/audio/2018/ug/ug180330.mp3",
		"duration": 1760,
		"size": "14.1M",
		"artistId": 63,
		"artistName": "无尽恩典",
		"path": "https://rawcdn.githack.com/quiet324/LiangYouRadioResource201813/ug20180330/ug/ug180330.mp3",
		"id": 63180330
	},
	{
		"time": "20180403",
		"title": "更大的荣耀（2）",
		"downUrl": "http://txly2.net/ly/audio/2018/ug/ug180403.mp3",
		"duration": 1760,
		"size": "14.1M",
		"artistId": 63,
		"artistName": "无尽恩典",
		"path": "https://rawcdn.githack.com/quiet324/LiangYouRadioResource201814/ug20180403/ug/ug180403.mp3",
		"id": 63180403
	},
	{
		"time": "20180402",
		"title": "更大的荣耀（1）",
		"downUrl": "http://txly2.net/ly/audio/2018/ug/ug180402.mp3",
		"duration": 1760,
		"size": "14.1M",
		"artistId": 63,
		"artistName": "无尽恩典",
		"path": "https://rawcdn.githack.com/quiet324/LiangYouRadioResource201814/ug20180402/ug/ug180402.mp3",
		"id": 63180402
	},
	{
		"time": "20180404",
		"title": "恩典与救赎（1）",
		"downUrl": "http://txly2.net/ly/audio/2018/ug/ug180404.mp3",
		"duration": 1760,
		"size": "14.1M",
		"artistId": 63,
		"artistName": "无尽恩典",
		"path": "https://rawcdn.githack.com/quiet324/LiangYouRadioResource201814/ug20180404/ug/ug180404.mp3",
		"id": 63180404
	},
	{
		"time": "20180405",
		"title": "恩典与救赎（2）",
		"downUrl": "http://txly2.net/ly/audio/2018/ug/ug180405.mp3",
		"duration": 1760,
		"size": "14.1M",
		"artistId": 63,
		"artistName": "无尽恩典",
		"path": "https://rawcdn.githack.com/quiet324/LiangYouRadioResource201814/ug20180405/ug/ug180405.mp3",
		"id": 63180405
	},
	{
		"time": "20180406",
		"title": "认识恩典更多",
		"downUrl": "http://txly2.net/ly/audio/2018/ug/ug180406.mp3",
		"duration": 1760,
		"size": "14.1M",
		"artistId": 63,
		"artistName": "无尽恩典",
		"path": "https://rawcdn.githack.com/quiet324/LiangYouRadioResource201814/ug20180406/ug/ug180406.mp3",
		"id": 63180406
	},
	{
		"time": "20180409",
		"title": "在忧虑的尽头（1）",
		"downUrl": "http://txly2.net/ly/audio/2018/ug/ug180409.mp3",
		"duration": 1760,
		"size": "14.1M",
		"artistId": 63,
		"artistName": "无尽恩典",
		"path": "https://rawcdn.githack.com/quiet324/LiangYouRadioResource201815/ug20180409/ug/ug180409.mp3",
		"id": 63180409
	},
	{
		"time": "20180410",
		"title": "在忧虑的尽头（2）",
		"downUrl": "http://txly2.net/ly/audio/2018/ug/ug180410.mp3",
		"duration": 1760,
		"size": "14.1M",
		"artistId": 63,
		"artistName": "无尽恩典",
		"path": "https://rawcdn.githack.com/quiet324/LiangYouRadioResource201815/ug20180410/ug/ug180410.mp3",
		"id": 63180410
	},
	{
		"time": "20180411",
		"title": "每个人都很重要（1）",
		"downUrl": "http://txly2.net/ly/audio/2018/ug/ug180411.mp3",
		"duration": 1760,
		"size": "14.1M",
		"artistId": 63,
		"artistName": "无尽恩典",
		"path": "https://rawcdn.githack.com/quiet324/LiangYouRadioResource201815/ug20180411/ug/ug180411.mp3",
		"id": 63180411
	},
	{
		"time": "20180412",
		"title": "每个人都很重要（2）",
		"downUrl": "http://txly2.net/ly/audio/2018/ug/ug180412.mp3",
		"duration": 1760,
		"size": "14.1M",
		"artistId": 63,
		"artistName": "无尽恩典",
		"path": "https://rawcdn.githack.com/quiet324/LiangYouRadioResource201816/ug20180412/ug/ug180412.mp3",
		"id": 63180412
	},
	{
		"time": "20180413",
		"title": "我们工作的价值",
		"downUrl": "http://txly2.net/ly/audio/2018/ug/ug180413.mp3",
		"duration": 1760,
		"size": "14.1M",
		"artistId": 63,
		"artistName": "无尽恩典",
		"path": "https://rawcdn.githack.com/quiet324/LiangYouRadioResource201816/ug20180413/ug/ug180413.mp3",
		"id": 63180413
	},
	{
		"time": "20180416",
		"title": "你说，我是王（1）",
		"downUrl": "http://txly2.net/ly/audio/2018/ug/ug180416.mp3",
		"duration": 1760,
		"size": "14.1M",
		"artistId": 63,
		"artistName": "无尽恩典",
		"path": "https://rawcdn.githack.com/quiet324/LiangYouRadioResource201816/ug20180416/ug/ug180416.mp3",
		"id": 63180416
	},
	{
		"time": "20180417",
		"title": "你说，我是王（2）",
		"downUrl": "http://txly2.net/ly/audio/2018/ug/ug180417.mp3",
		"duration": 1760,
		"size": "14.1M",
		"artistId": 63,
		"artistName": "无尽恩典",
		"path": "https://rawcdn.githack.com/quiet324/LiangYouRadioResource201816/ug20180417/ug/ug180417.mp3",
		"id": 63180417
	},
	{
		"time": "20180418",
		"title": "我升上高天（1）",
		"downUrl": "http://txly2.net/ly/audio/2018/ug/ug180418.mp3",
		"duration": 1760,
		"size": "14.1M",
		"artistId": 63,
		"artistName": "无尽恩典",
		"path": "https://rawcdn.githack.com/quiet324/LiangYouRadioResource201816/ug20180418/ug/ug180418.mp3",
		"id": 63180418
	},
	{
		"time": "20180419",
		"title": "我升上高天（2）",
		"downUrl": "http://txly2.net/ly/audio/2018/ug/ug180419.mp3",
		"duration": 1760,
		"size": "14.1M",
		"artistId": 63,
		"artistName": "无尽恩典",
		"path": "https://rawcdn.githack.com/quiet324/LiangYouRadioResource201816/ug20180419/ug/ug180419.mp3",
		"id": 63180419
	},
	{
		"time": "20180420",
		"title": "完全的喜乐（1）",
		"downUrl": "http://txly2.net/ly/audio/2018/ug/ug180420.mp3",
		"duration": 1760,
		"size": "14.1M",
		"artistId": 63,
		"artistName": "无尽恩典",
		"path": "https://rawcdn.githack.com/quiet324/LiangYouRadioResource201816/ug20180420/ug/ug180420.mp3",
		"id": 63180420
	},
	{
		"time": "20180423",
		"title": "完全的喜乐（2）",
		"downUrl": "http://txly2.net/ly/audio/2018/ug/ug180423.mp3",
		"duration": 1760,
		"size": "14.1M",
		"artistId": 63,
		"artistName": "无尽恩典",
		"path": "https://rawcdn.githack.com/quiet324/LiangYouRadioResource201817/ug20180423/ug/ug180423.mp3",
		"id": 63180423
	},
	{
		"time": "20180424",
		"title": "丰富的喜乐（1）",
		"downUrl": "http://txly2.net/ly/audio/2018/ug/ug180424.mp3",
		"duration": 1760,
		"size": "14.1M",
		"artistId": 63,
		"artistName": "无尽恩典",
		"path": "https://rawcdn.githack.com/quiet324/LiangYouRadioResource201817/ug20180424/ug/ug180424.mp3",
		"id": 63180424
	},
	{
		"time": "20180425",
		"title": "丰富的喜乐（2）",
		"downUrl": "http://txly2.net/ly/audio/2018/ug/ug180425.mp3",
		"duration": 1760,
		"size": "14.1M",
		"artistId": 63,
		"artistName": "无尽恩典",
		"path": "https://rawcdn.githack.com/quiet324/LiangYouRadioResource201817/ug20180425/ug/ug180425.mp3",
		"id": 63180425
	},
	{
		"time": "20180426",
		"title": "以基督为中心的敬拜",
		"downUrl": "http://txly2.net/ly/audio/2018/ug/ug180426.mp3",
		"duration": 1760,
		"size": "14.1M",
		"artistId": 63,
		"artistName": "无尽恩典",
		"path": "https://rawcdn.githack.com/quiet324/LiangYouRadioResource201817/ug20180426/ug/ug180426.mp3",
		"id": 63180426
	},
	{
		"time": "20180427",
		"title": "停不下来的喜乐（1）",
		"downUrl": "http://txly2.net/ly/audio/2018/ug/ug180427.mp3",
		"duration": 1760,
		"size": "14.1M",
		"artistId": 63,
		"artistName": "无尽恩典",
		"path": "https://rawcdn.githack.com/quiet324/LiangYouRadioResource201817/ug20180427/ug/ug180427.mp3",
		"id": 63180427
	},
	{
		"time": "20180430",
		"title": "停不下来的喜乐（2）",
		"downUrl": "http://txly2.net/ly/audio/2018/ug/ug180430.mp3",
		"duration": 1760,
		"size": "14.1M",
		"artistId": 63,
		"artistName": "无尽恩典",
		"path": "https://rawcdn.githack.com/quiet324/LiangYouRadioResource201818/ug20180430/ug/ug180430.mp3",
		"id": 63180430
	},
	{
		"time": "20180501",
		"title": "进退两难的困境（1）",
		"downUrl": "http://txly2.net/ly/audio/2018/ug/ug180501.mp3",
		"duration": 1760,
		"size": "14.1M",
		"artistId": 63,
		"artistName": "无尽恩典",
		"path": "https://rawcdn.githack.com/quiet324/LiangYouRadioResource201818/ug20180501/ug/ug180501.mp3",
		"id": 63180501
	},
	{
		"time": "20180502",
		"title": "进退两难的困境（2）",
		"downUrl": "http://txly2.net/ly/audio/2018/ug/ug180502.mp3",
		"duration": 1760,
		"size": "14.1M",
		"artistId": 63,
		"artistName": "无尽恩典",
		"path": "https://rawcdn.githack.com/quiet324/LiangYouRadioResource201818/ug20180502/ug/ug180502.mp3",
		"id": 63180502
	},
	{
		"time": "20180503",
		"title": "蔡博恩特别访谈",
		"downUrl": "http://txly2.net/ly/audio/2018/ug/ug180503.mp3",
		"duration": 1760,
		"size": "14.1M",
		"artistId": 63,
		"artistName": "无尽恩典",
		"path": "https://rawcdn.githack.com/quiet324/LiangYouRadioResource201818/ug20180503/ug/ug180503.mp3",
		"id": 63180503
	},
	{
		"time": "20180504",
		"title": "喜乐的记号（1）",
		"downUrl": "http://txly2.net/ly/audio/2018/ug/ug180504.mp3",
		"duration": 1760,
		"size": "14.1M",
		"artistId": 63,
		"artistName": "无尽恩典",
		"path": "https://rawcdn.githack.com/quiet324/LiangYouRadioResource201818/ug20180504/ug/ug180504.mp3",
		"id": 63180504
	},
	{
		"time": "20180507",
		"title": "喜乐的记号（2）",
		"downUrl": "http://txly2.net/ly/audio/2018/ug/ug180507.mp3",
		"duration": 1760,
		"size": "14.1M",
		"artistId": 63,
		"artistName": "无尽恩典",
		"path": "https://rawcdn.githack.com/quiet324/LiangYouRadioResource201819/ug20180507/ug/ug180507.mp3",
		"id": 63180507
	},
	{
		"time": "20180508",
		"title": "谦卑的喜乐（1）",
		"downUrl": "http://txly2.net/ly/audio/2018/ug/ug180508.mp3",
		"duration": 1760,
		"size": "14.1M",
		"artistId": 63,
		"artistName": "无尽恩典",
		"path": "https://rawcdn.githack.com/quiet324/LiangYouRadioResource201819/ug20180508/ug/ug180508.mp3",
		"id": 63180508
	},
	{
		"time": "20180509",
		"title": "谦卑的喜乐（2）",
		"downUrl": "http://txly2.net/ly/audio/2018/ug/ug180509.mp3",
		"duration": 1760,
		"size": "14.1M",
		"artistId": 63,
		"artistName": "无尽恩典",
		"path": "https://rawcdn.githack.com/quiet324/LiangYouRadioResource201819/ug20180509/ug/ug180509.mp3",
		"id": 63180509
	},
	{
		"time": "20180510",
		"title": "蔡博恩特别访谈（2）",
		"downUrl": "http://txly2.net/ly/audio/2018/ug/ug180510.mp3",
		"duration": 1760,
		"size": "14.1M",
		"artistId": 63,
		"artistName": "无尽恩典",
		"path": "https://rawcdn.githack.com/quiet324/LiangYouRadioResource201819/ug20180510/ug/ug180510.mp3",
		"id": 63180510
	},
	{
		"time": "20180511",
		"title": "牺牲的快乐（1）",
		"downUrl": "http://txly2.net/ly/audio/2018/ug/ug180511.mp3",
		"duration": 1760,
		"size": "14.1M",
		"artistId": 63,
		"artistName": "无尽恩典",
		"path": "https://rawcdn.githack.com/quiet324/LiangYouRadioResource201819/ug20180511/ug/ug180511.mp3",
		"id": 63180511
	},
	{
		"time": "20180514",
		"title": "牺牲的快乐（2）",
		"downUrl": "http://txly2.net/ly/audio/2018/ug/ug180514.mp3",
		"duration": 1760,
		"size": "14.1M",
		"artistId": 63,
		"artistName": "无尽恩典",
		"path": "https://rawcdn.githack.com/quiet324/LiangYouRadioResource201820/ug20180514/ug/ug180514.mp3",
		"id": 63180514
	},
	{
		"time": "20180515",
		"title": "分享蔡博恩的著作",
		"downUrl": "http://txly2.net/ly/audio/2018/ug/ug180515.mp3",
		"duration": 1760,
		"size": "14.1M",
		"artistId": 63,
		"artistName": "无尽恩典",
		"path": "https://rawcdn.githack.com/quiet324/LiangYouRadioResource201820/ug20180515/ug/ug180515.mp3",
		"id": 63180515
	},
	{
		"time": "20180516",
		"title": "一位母亲的祷告（1）",
		"downUrl": "http://txly2.net/ly/audio/2018/ug/ug180516.mp3",
		"duration": 1760,
		"size": "14.1M",
		"artistId": 63,
		"artistName": "无尽恩典",
		"path": "https://rawcdn.githack.com/quiet324/LiangYouRadioResource201820/ug20180516/ug/ug180516.mp3",
		"id": 63180516
	},
	{
		"time": "20180517",
		"title": "一位母亲的祷告（2）",
		"downUrl": "http://txly2.net/ly/audio/2018/ug/ug180517.mp3",
		"duration": 1760,
		"size": "14.1M",
		"artistId": 63,
		"artistName": "无尽恩典",
		"path": "https://rawcdn.githack.com/quiet324/LiangYouRadioResource201820/ug20180517/ug/ug180517.mp3",
		"id": 63180517
	},
	{
		"time": "20180518",
		"title": "以喜乐的心接受恩典",
		"downUrl": "http://txly2.net/ly/audio/2018/ug/ug180518.mp3",
		"duration": 1760,
		"size": "14.1M",
		"artistId": 63,
		"artistName": "无尽恩典",
		"path": "https://rawcdn.githack.com/quiet324/LiangYouRadioResource201820/ug20180518/ug/ug180518.mp3",
		"id": 63180518
	},
	{
		"time": "20180523",
		"title": "喜乐的眼睛（1）",
		"downUrl": "http://txly2.net/ly/audio/2018/ug/ug180523.mp3",
		"duration": 1760,
		"size": "14.1M",
		"artistId": 63,
		"artistName": "无尽恩典",
		"path": "https://rawcdn.githack.com/quiet324/LiangYouRadioResource201821/ug20180523/ug/ug180523.mp3",
		"id": 63180523
	},
	{
		"time": "20180521",
		"title": "超越喜悦（1）",
		"downUrl": "http://txly2.net/ly/audio/2018/ug/ug180521.mp3",
		"duration": 1760,
		"size": "14.1M",
		"artistId": 63,
		"artistName": "无尽恩典",
		"path": "https://rawcdn.githack.com/quiet324/LiangYouRadioResource201821/ug20180521/ug/ug180521.mp3",
		"id": 63180521
	},
	{
		"time": "20180522",
		"title": "超越喜悦（2）",
		"downUrl": "http://txly2.net/ly/audio/2018/ug/ug180522.mp3",
		"duration": 1760,
		"size": "14.1M",
		"artistId": 63,
		"artistName": "无尽恩典",
		"path": "https://rawcdn.githack.com/quiet324/LiangYouRadioResource201821/ug20180522/ug/ug180522.mp3",
		"id": 63180522
	},
	{
		"time": "20180524",
		"title": "喜乐的眼睛（2）",
		"downUrl": "http://txly2.net/ly/audio/2018/ug/ug180524.mp3",
		"duration": 1760,
		"size": "14.1M",
		"artistId": 63,
		"artistName": "无尽恩典",
		"path": "https://rawcdn.githack.com/quiet324/LiangYouRadioResource201821/ug20180524/ug/ug180524.mp3",
		"id": 63180524
	},
	{
		"time": "20180525",
		"title": "这里发生了什么事？（1）",
		"downUrl": "http://txly2.net/ly/audio/2018/ug/ug180525.mp3",
		"duration": 1760,
		"size": "14.1M",
		"artistId": 63,
		"artistName": "无尽恩典",
		"path": "https://rawcdn.githack.com/quiet324/LiangYouRadioResource201821/ug20180525/ug/ug180525.mp3",
		"id": 63180525
	},
	{
		"time": "20180528",
		"title": "这里发生了什么事？（2）",
		"downUrl": "http://txly2.net/ly/audio/2018/ug/ug180528.mp3",
		"duration": 1760,
		"size": "14.1M",
		"artistId": 63,
		"artistName": "无尽恩典",
		"path": "https://rawcdn.githack.com/quiet324/LiangYouRadioResource201822/ug20180528/ug/ug180528.mp3",
		"id": 63180528
	},
	{
		"time": "20180529",
		"title": "盼望带来的喜乐（1）",
		"downUrl": "http://txly2.net/ly/audio/2018/ug/ug180529.mp3",
		"duration": 1760,
		"size": "14.1M",
		"artistId": 63,
		"artistName": "无尽恩典",
		"path": "https://rawcdn.githack.com/quiet324/LiangYouRadioResource201822/ug20180529/ug/ug180529.mp3",
		"id": 63180529
	},
	{
		"time": "20180530",
		"title": "盼望带来的喜乐（2）",
		"downUrl": "http://txly2.net/ly/audio/2018/ug/ug180530.mp3",
		"duration": 1760,
		"size": "14.1M",
		"artistId": 63,
		"artistName": "无尽恩典",
		"path": "https://rawcdn.githack.com/quiet324/LiangYouRadioResource201822/ug20180530/ug/ug180530.mp3",
		"id": 63180530
	},
	{
		"time": "20180531",
		"title": "和解带来的喜悦（1）",
		"downUrl": "http://txly2.net/ly/audio/2018/ug/ug180531.mp3",
		"duration": 1760,
		"size": "14.1M",
		"artistId": 63,
		"artistName": "无尽恩典",
		"path": "https://rawcdn.githack.com/quiet324/LiangYouRadioResource201822/ug20180531/ug/ug180531.mp3",
		"id": 63180531
	},
	{
		"time": "20180601",
		"title": "和解带来的喜悦（2）",
		"downUrl": "http://txly2.net/ly/audio/2018/ug/ug180601.mp3",
		"duration": 1760,
		"size": "14.1M",
		"artistId": 63,
		"artistName": "无尽恩典",
		"path": "https://rawcdn.githack.com/quiet324/LiangYouRadioResource201822/ug20180601/ug/ug180601.mp3",
		"id": 63180601
	},
	{
		"time": "20180604",
		"title": "接近喜乐（1）",
		"downUrl": "http://txly2.net/ly/audio/2018/ug/ug180604.mp3",
		"duration": 1760,
		"size": "14.1M",
		"artistId": 63,
		"artistName": "无尽恩典",
		"path": "https://rawcdn.githack.com/quiet324/LiangYouRadioResource201823/ug20180604/ug/ug180604.mp3",
		"id": 63180604
	},
	{
		"time": "20180605",
		"title": "接近喜乐（2）",
		"downUrl": "http://txly2.net/ly/audio/2018/ug/ug180605.mp3",
		"duration": 1760,
		"size": "14.1M",
		"artistId": 63,
		"artistName": "无尽恩典",
		"path": "https://rawcdn.githack.com/quiet324/LiangYouRadioResource201823/ug20180605/ug/ug180605.mp3",
		"id": 63180605
	},
	{
		"time": "20180606",
		"title": "单纯的喜乐（1）",
		"downUrl": "http://txly2.net/ly/audio/2018/ug/ug180606.mp3",
		"duration": 1760,
		"size": "14.1M",
		"artistId": 63,
		"artistName": "无尽恩典",
		"path": "https://rawcdn.githack.com/quiet324/LiangYouRadioResource201823/ug20180606/ug/ug180606.mp3",
		"id": 63180606
	},
	{
		"time": "20180607",
		"title": "单纯的喜乐（2）",
		"downUrl": "http://txly2.net/ly/audio/2018/ug/ug180607.mp3",
		"duration": 1760,
		"size": "14.1M",
		"artistId": 63,
		"artistName": "无尽恩典",
		"path": "https://rawcdn.githack.com/quiet324/LiangYouRadioResource201823/ug20180607/ug/ug180607.mp3",
		"id": 63180607
	},
	{
		"time": "20180608",
		"title": "满足的喜乐（1）",
		"downUrl": "http://txly2.net/ly/audio/2018/ug/ug180608.mp3",
		"duration": 1760,
		"size": "14.1M",
		"artistId": 63,
		"artistName": "无尽恩典",
		"path": "https://rawcdn.githack.com/quiet324/LiangYouRadioResource201823/ug20180608/ug/ug180608.mp3",
		"id": 63180608
	},
	{
		"time": "20180611",
		"title": "满足的喜乐（2）",
		"downUrl": "http://txly2.net/ly/audio/2018/ug/ug180611.mp3",
		"duration": 1760,
		"size": "14.1M",
		"artistId": 63,
		"artistName": "无尽恩典",
		"path": "https://rawcdn.githack.com/quiet324/LiangYouRadioResource201824/ug20180611/ug/ug180611.mp3",
		"id": 63180611
	},
	{
		"time": "20180612",
		"title": "慷慨的喜乐（1）",
		"downUrl": "http://txly2.net/ly/audio/2018/ug/ug180612.mp3",
		"duration": 1760,
		"size": "14.1M",
		"artistId": 63,
		"artistName": "无尽恩典",
		"path": "https://rawcdn.githack.com/quiet324/LiangYouRadioResource201824/ug20180612/ug/ug180612.mp3",
		"id": 63180612
	},
	{
		"time": "20180613",
		"title": "慷慨的喜乐（2）",
		"downUrl": "http://txly2.net/ly/audio/2018/ug/ug180613.mp3",
		"duration": 1760,
		"size": "14.1M",
		"artistId": 63,
		"artistName": "无尽恩典",
		"path": "https://rawcdn.githack.com/quiet324/LiangYouRadioResource201824/ug20180613/ug/ug180613.mp3",
		"id": 63180613
	},
	{
		"time": "20180614",
		"title": "生命的传承（1）",
		"downUrl": "http://txly2.net/ly/audio/2018/ug/ug180614.mp3",
		"duration": 1760,
		"size": "14.1M",
		"artistId": 63,
		"artistName": "无尽恩典",
		"path": "https://rawcdn.githack.com/quiet324/LiangYouRadioResource201824/ug20180614/ug/ug180614.mp3",
		"id": 63180614
	},
	{
		"time": "20180615",
		"title": "生命的传承（2）",
		"downUrl": "http://txly2.net/ly/audio/2018/ug/ug180615.mp3",
		"duration": 1760,
		"size": "14.1M",
		"artistId": 63,
		"artistName": "无尽恩典",
		"path": "https://rawcdn.githack.com/quiet324/LiangYouRadioResource201824/ug20180615/ug/ug180615.mp3",
		"id": 63180615
	},
	{
		"time": "20180618",
		"title": "做个蒙福的人（1）",
		"downUrl": "http://txly2.net/ly/audio/2018/ug/ug180618.mp3",
		"duration": 1760,
		"size": "14.1M",
		"artistId": 63,
		"artistName": "无尽恩典",
		"path": "https://rawcdn.githack.com/quiet324/LiangYouRadioResource201825/ug20180618/ug/ug180618.mp3",
		"id": 63180618
	},
	{
		"time": "20180619",
		"title": "做个蒙福的人（2）",
		"downUrl": "http://txly2.net/ly/audio/2018/ug/ug180619.mp3",
		"duration": 1760,
		"size": "14.1M",
		"artistId": 63,
		"artistName": "无尽恩典",
		"path": "https://rawcdn.githack.com/quiet324/LiangYouRadioResource201825/ug20180619/ug/ug180619.mp3",
		"id": 63180619
	},
	{
		"time": "20180620",
		"title": "噢，向神献上感恩（1）",
		"downUrl": "http://txly2.net/ly/audio/2018/ug/ug180620.mp3",
		"duration": 1760,
		"size": "14.1M",
		"artistId": 63,
		"artistName": "无尽恩典",
		"path": "https://rawcdn.githack.com/quiet324/LiangYouRadioResource201825/ug20180620/ug/ug180620.mp3",
		"id": 63180620
	},
	{
		"time": "20180621",
		"title": "噢，向神献上感恩（2）",
		"downUrl": "http://txly2.net/ly/audio/2018/ug/ug180621.mp3",
		"duration": 1760,
		"size": "14.1M",
		"artistId": 63,
		"artistName": "无尽恩典",
		"path": "https://rawcdn.githack.com/quiet324/LiangYouRadioResource201825/ug20180621/ug/ug180621.mp3",
		"id": 63180621
	},
	{
		"time": "20180622",
		"title": "普天下当向耶和华欢呼！（1）",
		"downUrl": "http://txly2.net/ly/audio/2018/ug/ug180622.mp3",
		"duration": 1760,
		"size": "14.1M",
		"artistId": 63,
		"artistName": "无尽恩典",
		"path": "https://rawcdn.githack.com/quiet324/LiangYouRadioResource201825/ug20180622/ug/ug180622.mp3",
		"id": 63180622
	},
	{
		"time": "20180625",
		"title": "普天下当向耶和华欢呼！（2）",
		"downUrl": "http://txly2.net/ly/audio/2018/ug/ug180625.mp3",
		"duration": 1760,
		"size": "14.1M",
		"artistId": 63,
		"artistName": "无尽恩典",
		"path": "https://rawcdn.githack.com/quiet324/LiangYouRadioResource201826/ug20180625/ug/ug180625.mp3",
		"id": 63180625
	},
	{
		"time": "20180626",
		"title": "我爱耶和华（1）",
		"downUrl": "http://txly2.net/ly/audio/2018/ug/ug180626.mp3",
		"duration": 1760,
		"size": "14.1M",
		"artistId": 63,
		"artistName": "无尽恩典",
		"path": "https://rawcdn.githack.com/quiet324/LiangYouRadioResource201826/ug20180626/ug/ug180626.mp3",
		"id": 63180626
	},
	{
		"time": "20180627",
		"title": "我爱耶和华（2）",
		"downUrl": "http://txly2.net/ly/audio/2018/ug/ug180627.mp3",
		"duration": 1760,
		"size": "14.1M",
		"artistId": 63,
		"artistName": "无尽恩典",
		"path": "https://rawcdn.githack.com/quiet324/LiangYouRadioResource201826/ug20180627/ug/ug180627.mp3",
		"id": 63180627
	},
	{
		"time": "20180628",
		"title": "宣告神的荣耀（1）",
		"downUrl": "http://txly2.net/ly/audio/2018/ug/ug180628.mp3",
		"duration": 1760,
		"size": "14.1M",
		"artistId": 63,
		"artistName": "无尽恩典",
		"path": "https://rawcdn.githack.com/quiet324/LiangYouRadioResource201826/ug20180628/ug/ug180628.mp3",
		"id": 63180628
	},
	{
		"time": "20180629",
		"title": "宣告神的荣耀（2）",
		"downUrl": "http://txly2.net/ly/audio/2018/ug/ug180629.mp3",
		"duration": 1760,
		"size": "14.1M",
		"artistId": 63,
		"artistName": "无尽恩典",
		"path": "https://rawcdn.githack.com/quiet324/LiangYouRadioResource201826/ug20180629/ug/ug180629.mp3",
		"id": 63180629
	},
	{
		"time": "20180702",
		"title": "神的话语和荣耀（1）",
		"downUrl": "http://txly2.net/ly/audio/2018/ug/ug180702.mp3",
		"duration": 1760,
		"size": "14.1M",
		"artistId": 63,
		"artistName": "无尽恩典",
		"path": "https://rawcdn.githack.com/quiet324/LiangYouRadioResource201827/ug20180702/ug/ug180702.mp3",
		"id": 63180702
	},
	{
		"time": "20180703",
		"title": "神的话语和荣耀（2）",
		"downUrl": "http://txly2.net/ly/audio/2018/ug/ug180703.mp3",
		"duration": 1760,
		"size": "14.1M",
		"artistId": 63,
		"artistName": "无尽恩典",
		"path": "https://rawcdn.githack.com/quiet324/LiangYouRadioResource201827/ug20180703/ug/ug180703.mp3",
		"id": 63180703
	},
	{
		"time": "20180704",
		"title": "全人类之歌（1）",
		"downUrl": "http://txly2.net/ly/audio/2018/ug/ug180704.mp3",
		"duration": 1760,
		"size": "14.1M",
		"artistId": 63,
		"artistName": "无尽恩典",
		"path": "https://rawcdn.githack.com/quiet324/LiangYouRadioResource201827/ug20180704/ug/ug180704.mp3",
		"id": 63180704
	},
	{
		"time": "20180705",
		"title": "全人类之歌（2）",
		"downUrl": "http://txly2.net/ly/audio/2018/ug/ug180705.mp3",
		"duration": 1760,
		"size": "14.1M",
		"artistId": 63,
		"artistName": "无尽恩典",
		"path": "https://rawcdn.githack.com/quiet324/LiangYouRadioResource201827/ug20180705/ug/ug180705.mp3",
		"id": 63180705
	},
	{
		"time": "20180706",
		"title": "藏身之处（1）",
		"downUrl": "http://txly2.net/ly/audio/2018/ug/ug180706.mp3",
		"duration": 1760,
		"size": "14.1M",
		"artistId": 63,
		"artistName": "无尽恩典",
		"path": "https://rawcdn.githack.com/quiet324/LiangYouRadioResource201827/ug20180706/ug/ug180706.mp3",
		"id": 63180706
	},
	{
		"time": "20180709",
		"title": "藏身之处（2）",
		"downUrl": "http://txly2.net/ly/audio/2018/ug/ug180709.mp3",
		"duration": 1760,
		"size": "14.1M",
		"artistId": 63,
		"artistName": "无尽恩典",
		"path": "https://rawcdn.githack.com/quiet324/LiangYouRadioResource201828/ug20180709/ug/ug180709.mp3",
		"id": 63180709
	},
	{
		"time": "20180710",
		"title": "他们为什么获得靠窗座位？（1）",
		"downUrl": "http://txly2.net/ly/audio/2018/ug/ug180710.mp3",
		"duration": 1760,
		"size": "14.1M",
		"artistId": 63,
		"artistName": "无尽恩典",
		"path": "https://rawcdn.githack.com/quiet324/LiangYouRadioResource201828/ug20180710/ug/ug180710.mp3",
		"id": 63180710
	},
	{
		"time": "20180711",
		"title": "他们为什么获得靠窗座位？（2）",
		"downUrl": "http://txly2.net/ly/audio/2018/ug/ug180711.mp3",
		"duration": 1760,
		"size": "14.1M",
		"artistId": 63,
		"artistName": "无尽恩典",
		"path": "https://rawcdn.githack.com/quiet324/LiangYouRadioResource201828/ug20180711/ug/ug180711.mp3",
		"id": 63180711
	},
	{
		"time": "20180712",
		"title": "黑夜的盼望（1）",
		"downUrl": "http://txly2.net/ly/audio/2018/ug/ug180712.mp3",
		"duration": 1760,
		"size": "14.1M",
		"artistId": 63,
		"artistName": "无尽恩典",
		"path": "https://rawcdn.githack.com/quiet324/LiangYouRadioResource201828/ug20180712/ug/ug180712.mp3",
		"id": 63180712
	},
	{
		"time": "20180713",
		"title": "黑夜的盼望（2）",
		"downUrl": "http://txly2.net/ly/audio/2018/ug/ug180713.mp3",
		"duration": 1760,
		"size": "14.1M",
		"artistId": 63,
		"artistName": "无尽恩典",
		"path": "https://rawcdn.githack.com/quiet324/LiangYouRadioResource201828/ug20180713/ug/ug180713.mp3",
		"id": 63180713
	},
	{
		"time": "20180716",
		"title": "听祷告的神（1）",
		"downUrl": "http://txly2.net/ly/audio/2018/ug/ug180716.mp3",
		"duration": 1760,
		"size": "14.1M",
		"artistId": 63,
		"artistName": "无尽恩典",
		"path": "https://rawcdn.githack.com/quiet324/LiangYouRadioResource201829/ug20180716/ug/ug180716.mp3",
		"id": 63180716
	},
	{
		"time": "20180717",
		"title": "听祷告的神（2）",
		"downUrl": "http://txly2.net/ly/audio/2018/ug/ug180717.mp3",
		"duration": 1760,
		"size": "14.1M",
		"artistId": 63,
		"artistName": "无尽恩典",
		"path": "https://rawcdn.githack.com/quiet324/LiangYouRadioResource201829/ug20180717/ug/ug180717.mp3",
		"id": 63180717
	},
	{
		"time": "20180718",
		"title": "赐人荣耀冠冕的神（1）",
		"downUrl": "http://txly2.net/ly/audio/2018/ug/ug180718.mp3",
		"duration": 1760,
		"size": "14.1M",
		"artistId": 63,
		"artistName": "无尽恩典",
		"path": "https://rawcdn.githack.com/quiet324/LiangYouRadioResource201829/ug20180718/ug/ug180718.mp3",
		"id": 63180718
	},
	{
		"time": "20180719",
		"title": "赐人荣耀冠冕的神（2）",
		"downUrl": "http://txly2.net/ly/audio/2018/ug/ug180719.mp3",
		"duration": 1760,
		"size": "14.1M",
		"artistId": 63,
		"artistName": "无尽恩典",
		"path": "https://rawcdn.githack.com/quiet324/LiangYouRadioResource201829/ug20180719/ug/ug180719.mp3",
		"id": 63180719
	},
	{
		"time": "20180720",
		"title": "看顾保守人的神（1）",
		"downUrl": "http://txly2.net/ly/audio/2018/ug/ug180720.mp3",
		"duration": 1760,
		"size": "14.1M",
		"artistId": 63,
		"artistName": "无尽恩典",
		"path": "https://rawcdn.githack.com/quiet324/LiangYouRadioResource201829/ug20180720/ug/ug180720.mp3",
		"id": 63180720
	},
	{
		"time": "20180723",
		"title": "看顾保守人的神（2）",
		"downUrl": "http://txly2.net/ly/audio/2018/ug/ug180723.mp3",
		"duration": 1760,
		"size": "14.1M",
		"artistId": 63,
		"artistName": "无尽恩典",
		"path": "https://rawcdn.githack.com/quiet324/LiangYouRadioResource201830/ug20180723/ug/ug180723.mp3",
		"id": 63180723
	},
	{
		"time": "20180724",
		"title": "我们不过是尘土（1）",
		"downUrl": "http://txly2.net/ly/audio/2018/ug/ug180724.mp3",
		"duration": 1760,
		"size": "14.1M",
		"artistId": 63,
		"artistName": "无尽恩典",
		"path": "https://rawcdn.githack.com/quiet324/LiangYouRadioResource201830/ug20180724/ug/ug180724.mp3",
		"id": 63180724
	},
	{
		"time": "20180725",
		"title": "我们不过是尘土（2）",
		"downUrl": "http://txly2.net/ly/audio/2018/ug/ug180725.mp3",
		"duration": 1760,
		"size": "14.1M",
		"artistId": 63,
		"artistName": "无尽恩典",
		"path": "https://rawcdn.githack.com/quiet324/LiangYouRadioResource201830/ug20180725/ug/ug180725.mp3",
		"id": 63180725
	},
	{
		"time": "20180726",
		"title": "引领人的神（1）",
		"downUrl": "http://txly2.net/ly/audio/2018/ug/ug180726.mp3",
		"duration": 1760,
		"size": "14.1M",
		"artistId": 63,
		"artistName": "无尽恩典",
		"path": "https://rawcdn.githack.com/quiet324/LiangYouRadioResource201830/ug20180726/ug/ug180726.mp3",
		"id": 63180726
	},
	{
		"time": "20180727",
		"title": "引领人的神（2）",
		"downUrl": "http://txly2.net/ly/audio/2018/ug/ug180727.mp3",
		"duration": 1760,
		"size": "14.1M",
		"artistId": 63,
		"artistName": "无尽恩典",
		"path": "https://rawcdn.githack.com/quiet324/LiangYouRadioResource201830/ug20180727/ug/ug180727.mp3",
		"id": 63180727
	},
	{
		"time": "20180730",
		"title": "信实守约的神（1）",
		"downUrl": "http://txly2.net/ly/audio/2018/ug/ug180730.mp3",
		"duration": 1760,
		"size": "14.1M",
		"artistId": 63,
		"artistName": "无尽恩典",
		"path": "https://rawcdn.githack.com/quiet324/LiangYouRadioResource201831/ug20180730/ug/ug180730.mp3",
		"id": 63180730
	},
	{
		"time": "20180731",
		"title": "信实守约的神（2）",
		"downUrl": "http://txly2.net/ly/audio/2018/ug/ug180731.mp3",
		"duration": 1760,
		"size": "14.1M",
		"artistId": 63,
		"artistName": "无尽恩典",
		"path": "https://rawcdn.githack.com/quiet324/LiangYouRadioResource201831/ug20180731/ug/ug180731.mp3",
		"id": 63180731
	},
	{
		"time": "20180801",
		"title": "收养的福音（1）",
		"downUrl": "http://txly2.net/ly/audio/2018/ug/ug180801.mp3",
		"duration": 1760,
		"size": "14.1M",
		"artistId": 63,
		"artistName": "无尽恩典",
		"path": "https://rawcdn.githack.com/quiet324/LiangYouRadioResource201831/ug20180801/ug/ug180801.mp3",
		"id": 63180801
	},
	{
		"time": "20180802",
		"title": "收养的福音（2）",
		"downUrl": "http://txly2.net/ly/audio/2018/ug/ug180802.mp3",
		"duration": 1760,
		"size": "14.1M",
		"artistId": 63,
		"artistName": "无尽恩典",
		"path": "https://rawcdn.githack.com/quiet324/LiangYouRadioResource201831/ug20180802/ug/ug180802.mp3",
		"id": 63180802
	},
	{
		"time": "20180803",
		"title": "工作使命（1）",
		"downUrl": "http://txly2.net/ly/audio/2018/ug/ug180803.mp3",
		"duration": 1760,
		"size": "14.1M",
		"artistId": 63,
		"artistName": "无尽恩典",
		"path": "https://rawcdn.githack.com/quiet324/LiangYouRadioResource201831/ug20180803/ug/ug180803.mp3",
		"id": 63180803
	},
	{
		"time": "20180806",
		"title": "工作使命（2）",
		"downUrl": "http://txly2.net/ly/audio/2018/ug/ug180806.mp3",
		"duration": 1760,
		"size": "14.1M",
		"artistId": 63,
		"artistName": "无尽恩典",
		"path": "https://rawcdn.githack.com/quiet324/LiangYouRadioResource201832/ug20180806/ug/ug180806.mp3",
		"id": 63180806
	},
	{
		"time": "20180807",
		"title": "工作的目的（1）",
		"downUrl": "http://txly2.net/ly/audio/2018/ug/ug180807.mp3",
		"duration": 1760,
		"size": "14.1M",
		"artistId": 63,
		"artistName": "无尽恩典",
		"path": "https://rawcdn.githack.com/quiet324/LiangYouRadioResource201832/ug20180807/ug/ug180807.mp3",
		"id": 63180807
	},
	{
		"time": "20180808",
		"title": "工作的目的（2）",
		"downUrl": "http://txly2.net/ly/audio/2018/ug/ug180808.mp3",
		"duration": 1760,
		"size": "14.1M",
		"artistId": 63,
		"artistName": "无尽恩典",
		"path": "https://rawcdn.githack.com/quiet324/LiangYouRadioResource201832/ug20180808/ug/ug180808.mp3",
		"id": 63180808
	}
]