[
	{
		"time": "20181225",
		"title": "时代的灯塔",
		"downUrl": "http://txly2.net/ly/audio/2018/it/it181225.mp3",
		"duration": 1760,
		"size": "14.1M",
		"artistId": 41,
		"artistName": "与神同行",
		"path": "https://rawcdn.githack.com/quiet324/LiangYouRadioResource201852/it20181225/it/it181225.mp3",
		"id": 41181225
	},
	{
		"time": "20181226",
		"title": "肉体的挣扎（1）",
		"downUrl": "http://txly2.net/ly/audio/2018/it/it181226.mp3",
		"duration": 1760,
		"size": "14.1M",
		"artistId": 41,
		"artistName": "与神同行",
		"path": "https://rawcdn.githack.com/quiet324/LiangYouRadioResource201852/it20181226/it/it181226.mp3",
		"id": 41181226
	},
	{
		"time": "20181227",
		"title": "肉体的挣扎（2）",
		"downUrl": "http://txly2.net/ly/audio/2018/it/it181227.mp3",
		"duration": 1760,
		"size": "14.1M",
		"artistId": 41,
		"artistName": "与神同行",
		"path": "https://rawcdn.githack.com/quiet324/LiangYouRadioResource201852/it20181227/it/it181227.mp3",
		"id": 41181227
	},
	{
		"time": "20181228",
		"title": "试探的挣扎（1）",
		"downUrl": "http://txly2.net/ly/audio/2018/it/it181228.mp3",
		"duration": 1760,
		"size": "14.1M",
		"artistId": 41,
		"artistName": "与神同行",
		"path": "https://rawcdn.githack.com/quiet324/LiangYouRadioResource201852/it20181228/it/it181228.mp3",
		"id": 41181228
	},
	{
		"time": "20181231",
		"title": "试探的挣扎（2）",
		"downUrl": "http://txly2.net/ly/audio/2018/it/it181231.mp3",
		"duration": 1760,
		"size": "14.1M",
		"artistId": 41,
		"artistName": "与神同行",
		"path": "https://rawcdn.githack.com/quiet324/LiangYouRadioResource201901/it20181231/it/it181231.mp3",
		"id": 41181231
	},
	{
		"time": "20190101",
		"title": "罪疚的挣扎（1）",
		"downUrl": "http://txly2.net/ly/audio/2019/it/it190101.mp3",
		"duration": 1760,
		"size": "14.1M",
		"artistId": 41,
		"artistName": "与神同行",
		"path": "https://rawcdn.githack.com/quiet324/LiangYouRadioResource201901/it20190101/it/it190101.mp3",
		"id": 41190101
	},
	{
		"time": "20190102",
		"title": "罪疚的挣扎（2）",
		"downUrl": "http://txly2.net/ly/audio/2019/it/it190102.mp3",
		"duration": 1760,
		"size": "14.1M",
		"artistId": 41,
		"artistName": "与神同行",
		"path": "https://rawcdn.githack.com/quiet324/LiangYouRadioResource201901/it20190102/it/it190102.mp3",
		"id": 41190102
	},
	{
		"time": "20190103",
		"title": "不饶恕人的挣扎（1）",
		"downUrl": "http://txly2.net/ly/audio/2019/it/it190103.mp3",
		"duration": 1760,
		"size": "14.1M",
		"artistId": 41,
		"artistName": "与神同行",
		"path": "https://rawcdn.githack.com/quiet324/LiangYouRadioResource201901/it20190103/it/it190103.mp3",
		"id": 41190103
	},
	{
		"time": "20190104",
		"title": "不饶恕人的挣扎（2）",
		"downUrl": "http://txly2.net/ly/audio/2019/it/it190104.mp3",
		"duration": 1760,
		"size": "14.1M",
		"artistId": 41,
		"artistName": "与神同行",
		"path": "https://rawcdn.githack.com/quiet324/LiangYouRadioResource201901/it20190104/it/it190104.mp3",
		"id": 41190104
	},
	{
		"time": "20190107",
		"title": "嫉妒的挣扎（1）",
		"downUrl": "http://txly2.net/ly/audio/2019/it/it190107.mp3",
		"duration": 1760,
		"size": "14.1M",
		"artistId": 41,
		"artistName": "与神同行",
		"path": "https://rawcdn.githack.com/quiet324/LiangYouRadioResource201902/it20190107/it/it190107.mp3",
		"id": 41190107
	},
	{
		"time": "20190108",
		"title": "嫉妒的挣扎（2）",
		"downUrl": "http://txly2.net/ly/audio/2019/it/it190108.mp3",
		"duration": 1760,
		"size": "14.1M",
		"artistId": 41,
		"artistName": "与神同行",
		"path": "https://rawcdn.githack.com/quiet324/LiangYouRadioResource201902/it20190108/it/it190108.mp3",
		"id": 41190108
	},
	{
		"time": "20190109",
		"title": "疑惑的挣扎（1）",
		"downUrl": "http://txly2.net/ly/audio/2019/it/it190109.mp3",
		"duration": 1760,
		"size": "14.1M",
		"artistId": 41,
		"artistName": "与神同行",
		"path": "https://rawcdn.githack.com/quiet324/LiangYouRadioResource201902/it20190109/it/it190109.mp3",
		"id": 41190109
	},
	{
		"time": "20190110",
		"title": "疑惑的挣扎（2）",
		"downUrl": "http://txly2.net/ly/audio/2019/it/it190110.mp3",
		"duration": 1760,
		"size": "14.1M",
		"artistId": 41,
		"artistName": "与神同行",
		"path": "https://rawcdn.githack.com/quiet324/LiangYouRadioResource201902/it20190110/it/it190110.mp3",
		"id": 41190110
	},
	{
		"time": "20190111",
		"title": "妥协的结果",
		"downUrl": "http://txly2.net/ly/audio/2019/it/it190111.mp3",
		"duration": 1760,
		"size": "14.1M",
		"artistId": 41,
		"artistName": "与神同行",
		"path": "https://rawcdn.githack.com/quiet324/LiangYouRadioResource201902/it20190111/it/it190111.mp3",
		"id": 41190111
	},
	{
		"time": "20190114",
		"title": "悔改的呼召（1）",
		"downUrl": "http://txly2.net/ly/audio/2019/it/it190114.mp3",
		"duration": 1760,
		"size": "14.1M",
		"artistId": 41,
		"artistName": "与神同行",
		"path": "https://rawcdn.githack.com/quiet324/LiangYouRadioResource201903/it20190114/it/it190114.mp3",
		"id": 41190114
	},
	{
		"time": "20190115",
		"title": "悔改的呼召（2）",
		"downUrl": "http://txly2.net/ly/audio/2019/it/it190115.mp3",
		"duration": 1760,
		"size": "14.1M",
		"artistId": 41,
		"artistName": "与神同行",
		"path": "https://rawcdn.githack.com/quiet324/LiangYouRadioResource201903/it20190115/it/it190115.mp3",
		"id": 41190115
	},
	{
		"time": "20190116",
		"title": "逃兵的启示（1）",
		"downUrl": "http://txly2.net/ly/audio/2019/it/it190116.mp3",
		"duration": 1760,
		"size": "14.1M",
		"artistId": 41,
		"artistName": "与神同行",
		"path": "https://rawcdn.githack.com/quiet324/LiangYouRadioResource201903/it20190116/it/it190116.mp3",
		"id": 41190116
	},
	{
		"time": "20190117",
		"title": "逃兵的启示（2）",
		"downUrl": "http://txly2.net/ly/audio/2019/it/it190117.mp3",
		"duration": 1760,
		"size": "14.1M",
		"artistId": 41,
		"artistName": "与神同行",
		"path": "https://rawcdn.githack.com/quiet324/LiangYouRadioResource201903/it20190117/it/it190117.mp3",
		"id": 41190117
	},
	{
		"time": "20190118",
		"title": "环境失控吗？",
		"downUrl": "http://txly2.net/ly/audio/2019/it/it190118.mp3",
		"duration": 1760,
		"size": "14.1M",
		"artistId": 41,
		"artistName": "与神同行",
		"path": "https://rawcdn.githack.com/quiet324/LiangYouRadioResource201903/it20190118/it/it190118.mp3",
		"id": 41190118
	},
	{
		"time": "20190121",
		"title": "敬畏神（1）",
		"downUrl": "http://txly2.net/ly/audio/2019/it/it190121.mp3",
		"duration": 1760,
		"size": "14.1M",
		"artistId": 41,
		"artistName": "与神同行",
		"path": "https://rawcdn.githack.com/quiet324/LiangYouRadioResource201904/it20190121/it/it190121.mp3",
		"id": 41190121
	},
	{
		"time": "20190122",
		"title": "敬畏神（2）",
		"downUrl": "http://txly2.net/ly/audio/2019/it/it190122.mp3",
		"duration": 1760,
		"size": "14.1M",
		"artistId": 41,
		"artistName": "与神同行",
		"path": "https://rawcdn.githack.com/quiet324/LiangYouRadioResource201904/it20190122/it/it190122.mp3",
		"id": 41190122
	},
	{
		"time": "20190123",
		"title": "面对死亡",
		"downUrl": "http://txly2.net/ly/audio/2019/it/it190123.mp3",
		"duration": 1760,
		"size": "14.1M",
		"artistId": 41,
		"artistName": "与神同行",
		"path": "https://rawcdn.githack.com/quiet324/LiangYouRadioResource201904/it20190123/it/it190123.mp3",
		"id": 41190123
	},
	{
		"time": "20190124",
		"title": "受伤害的人",
		"downUrl": "http://txly2.net/ly/audio/2019/it/it190124.mp3",
		"duration": 1760,
		"size": "14.1M",
		"artistId": 41,
		"artistName": "与神同行",
		"path": "https://rawcdn.githack.com/quiet324/LiangYouRadioResource201904/it20190124/it/it190124.mp3",
		"id": 41190124
	},
	{
		"time": "20190125",
		"title": "单做好是不够的",
		"downUrl": "http://txly2.net/ly/audio/2019/it/it190125.mp3",
		"duration": 1760,
		"size": "14.1M",
		"artistId": 41,
		"artistName": "与神同行",
		"path": "https://rawcdn.githack.com/quiet324/LiangYouRadioResource201904/it20190125/it/it190125.mp3",
		"id": 41190125
	},
	{
		"time": "20190128",
		"title": "拒绝福音的人",
		"downUrl": "http://txly2.net/ly/audio/2019/it/it190128.mp3",
		"duration": 1760,
		"size": "14.1M",
		"artistId": 41,
		"artistName": "与神同行",
		"path": "https://rawcdn.githack.com/quiet324/LiangYouRadioResource201905/it20190128/it/it190128.mp3",
		"id": 41190128
	},
	{
		"time": "20190129",
		"title": "不能动摇的事",
		"downUrl": "http://txly2.net/ly/audio/2019/it/it190129.mp3",
		"duration": 1760,
		"size": "14.1M",
		"artistId": 41,
		"artistName": "与神同行",
		"path": "https://rawcdn.githack.com/quiet324/LiangYouRadioResource201905/it20190129/it/it190129.mp3",
		"id": 41190129
	},
	{
		"time": "20190130",
		"title": "成功的思想（1）",
		"downUrl": "http://txly2.net/ly/audio/2019/it/it190130.mp3",
		"duration": 1760,
		"size": "14.1M",
		"artistId": 41,
		"artistName": "与神同行",
		"path": "https://rawcdn.githack.com/quiet324/LiangYouRadioResource201905/it20190130/it/it190130.mp3",
		"id": 41190130
	},
	{
		"time": "20190131",
		"title": "成功的思想（2）",
		"downUrl": "http://txly2.net/ly/audio/2019/it/it190131.mp3",
		"duration": 1760,
		"size": "14.1M",
		"artistId": 41,
		"artistName": "与神同行",
		"path": "https://rawcdn.githack.com/quiet324/LiangYouRadioResource201905/it20190131/it/it190131.mp3",
		"id": 41190131
	},
	{
		"time": "20190201",
		"title": "成功的时间（1）",
		"downUrl": "http://txly2.net/ly/audio/2019/it/it190201.mp3",
		"duration": 1760,
		"size": "14.1M",
		"artistId": 41,
		"artistName": "与神同行",
		"path": "https://rawcdn.githack.com/quiet324/LiangYouRadioResource201905/it20190201/it/it190201.mp3",
		"id": 41190201
	},
	{
		"time": "20190204",
		"title": "成功的时间（2）",
		"downUrl": "http://txly2.net/ly/audio/2019/it/it190204.mp3",
		"duration": 1760,
		"size": "14.1M",
		"artistId": 41,
		"artistName": "与神同行",
		"path": "https://rawcdn.githack.com/quiet324/LiangYouRadioResource201906/it20190204/it/it190204.mp3",
		"id": 41190204
	},
	{
		"time": "20190205",
		"title": "坚忍的力量（1）",
		"downUrl": "http://txly2.net/ly/audio/2019/it/it190205.mp3",
		"duration": 1760,
		"size": "14.1M",
		"artistId": 41,
		"artistName": "与神同行",
		"path": "https://rawcdn.githack.com/quiet324/LiangYouRadioResource201906/it20190205/it/it190205.mp3",
		"id": 41190205
	},
	{
		"time": "20190206",
		"title": "坚忍的力量（2）",
		"downUrl": "http://txly2.net/ly/audio/2019/it/it190206.mp3",
		"duration": 1760,
		"size": "14.1M",
		"artistId": 41,
		"artistName": "与神同行",
		"path": "https://rawcdn.githack.com/quiet324/LiangYouRadioResource201906/it20190206/it/it190206.mp3",
		"id": 41190206
	},
	{
		"time": "20190207",
		"title": "信心带来成功",
		"downUrl": "http://txly2.net/ly/audio/2019/it/it190207.mp3",
		"duration": 1760,
		"size": "14.1M",
		"artistId": 41,
		"artistName": "与神同行",
		"path": "https://rawcdn.githack.com/quiet324/LiangYouRadioResource201906/it20190207/it/it190207.mp3",
		"id": 41190207
	},
	{
		"time": "20190208",
		"title": "生命的腐蚀（1）",
		"downUrl": "http://txly2.net/ly/audio/2019/it/it190208.mp3",
		"duration": 1760,
		"size": "14.1M",
		"artistId": 41,
		"artistName": "与神同行",
		"path": "https://rawcdn.githack.com/quiet324/LiangYouRadioResource201906/it20190208/it/it190208.mp3",
		"id": 41190208
	},
	{
		"time": "20190212",
		"title": "第二次的机会",
		"downUrl": "http://txly2.net/ly/audio/2019/it/it190212.mp3",
		"duration": 1760,
		"size": "14.1M",
		"artistId": 41,
		"artistName": "与神同行",
		"path": "https://rawcdn.githack.com/quiet324/LiangYouRadioResource201907/it20190212/it/it190212.mp3",
		"id": 41190212
	},
	{
		"time": "20190211",
		"title": "生命的腐蚀（2）",
		"downUrl": "http://txly2.net/ly/audio/2019/it/it190211.mp3",
		"duration": 1760,
		"size": "14.1M",
		"artistId": 41,
		"artistName": "与神同行",
		"path": "https://rawcdn.githack.com/quiet324/LiangYouRadioResource201907/it20190211/it/it190211.mp3",
		"id": 41190211
	},
	{
		"time": "20190213",
		"title": "使人自由的真理（1）",
		"downUrl": "http://txly2.net/ly/audio/2019/it/it190213.mp3",
		"duration": 1760,
		"size": "14.1M",
		"artistId": 41,
		"artistName": "与神同行",
		"path": "https://rawcdn.githack.com/quiet324/LiangYouRadioResource201907/it20190213/it/it190213.mp3",
		"id": 41190213
	},
	{
		"time": "20190214",
		"title": "使人自由的真理（2）",
		"downUrl": "http://txly2.net/ly/audio/2019/it/it190214.mp3",
		"duration": 1760,
		"size": "14.1M",
		"artistId": 41,
		"artistName": "与神同行",
		"path": "https://rawcdn.githack.com/quiet324/LiangYouRadioResource201907/it20190214/it/it190214.mp3",
		"id": 41190214
	},
	{
		"time": "20190215",
		"title": "使人自由的真理（3）",
		"downUrl": "http://txly2.net/ly/audio/2019/it/it190215.mp3",
		"duration": 1760,
		"size": "14.1M",
		"artistId": 41,
		"artistName": "与神同行",
		"path": "https://rawcdn.githack.com/quiet324/LiangYouRadioResource201907/it20190215/it/it190215.mp3",
		"id": 41190215
	},
	{
		"time": "20190218",
		"title": "使人自由的真理（4）",
		"downUrl": "http://txly2.net/ly/audio/2019/it/it190218.mp3",
		"duration": 1760,
		"size": "14.1M",
		"artistId": 41,
		"artistName": "与神同行",
		"path": "https://rawcdn.githack.com/quiet324/LiangYouRadioResource201908/it20190218/it/it190218.mp3",
		"id": 41190218
	},
	{
		"time": "20190219",
		"title": "使人自由的真理（5）",
		"downUrl": "http://txly2.net/ly/audio/2019/it/it190219.mp3",
		"duration": 1760,
		"size": "14.1M",
		"artistId": 41,
		"artistName": "与神同行",
		"path": "https://rawcdn.githack.com/quiet324/LiangYouRadioResource201908/it20190219/it/it190219.mp3",
		"id": 41190219
	},
	{
		"time": "20190220",
		"title": "使人自由的真理（6）",
		"downUrl": "http://txly2.net/ly/audio/2019/it/it190220.mp3",
		"duration": 1760,
		"size": "14.1M",
		"artistId": 41,
		"artistName": "与神同行",
		"path": "https://rawcdn.githack.com/quiet324/LiangYouRadioResource201908/it20190220/it/it190220.mp3",
		"id": 41190220
	},
	{
		"time": "20190221",
		"title": "使人自由的真理（7）",
		"downUrl": "http://txly2.net/ly/audio/2019/it/it190221.mp3",
		"duration": 1760,
		"size": "14.1M",
		"artistId": 41,
		"artistName": "与神同行",
		"path": "https://rawcdn.githack.com/quiet324/LiangYouRadioResource201908/it20190221/it/it190221.mp3",
		"id": 41190221
	},
	{
		"time": "20190222",
		"title": "使人自由的真理（8）",
		"downUrl": "http://txly2.net/ly/audio/2019/it/it190222.mp3",
		"duration": 1760,
		"size": "14.1M",
		"artistId": 41,
		"artistName": "与神同行",
		"path": "https://rawcdn.githack.com/quiet324/LiangYouRadioResource201908/it20190222/it/it190222.mp3",
		"id": 41190222
	},
	{
		"time": "20190225",
		"title": "使人自由的真理（9）",
		"downUrl": "http://txly2.net/ly/audio/2019/it/it190225.mp3",
		"duration": 1760,
		"size": "14.1M",
		"artistId": 41,
		"artistName": "与神同行",
		"path": "https://rawcdn.githack.com/quiet324/LiangYouRadioResource201909/it20190225/it/it190225.mp3",
		"id": 41190225
	},
	{
		"time": "20190226",
		"title": "使人自由的真理（10）",
		"downUrl": "http://txly2.net/ly/audio/2019/it/it190226.mp3",
		"duration": 1760,
		"size": "14.1M",
		"artistId": 41,
		"artistName": "与神同行",
		"path": "https://rawcdn.githack.com/quiet324/LiangYouRadioResource201909/it20190226/it/it190226.mp3",
		"id": 41190226
	},
	{
		"time": "20190227",
		"title": "撒但的策略（1）",
		"downUrl": "http://txly2.net/ly/audio/2019/it/it190227.mp3",
		"duration": 1760,
		"size": "14.1M",
		"artistId": 41,
		"artistName": "与神同行",
		"path": "https://rawcdn.githack.com/quiet324/LiangYouRadioResource201909/it20190227/it/it190227.mp3",
		"id": 41190227
	},
	{
		"time": "20190228",
		"title": "撒但的策略（2）",
		"downUrl": "http://txly2.net/ly/audio/2019/it/it190228.mp3",
		"duration": 1760,
		"size": "14.1M",
		"artistId": 41,
		"artistName": "与神同行",
		"path": "https://rawcdn.githack.com/quiet324/LiangYouRadioResource201909/it20190228/it/it190228.mp3",
		"id": 41190228
	},
	{
		"time": "20190301",
		"title": "在撒但的攻击下求存（1）",
		"downUrl": "http://txly2.net/ly/audio/2019/it/it190301.mp3",
		"duration": 1760,
		"size": "14.1M",
		"artistId": 41,
		"artistName": "与神同行",
		"path": "https://rawcdn.githack.com/quiet324/LiangYouRadioResource201909/it20190301/it/it190301.mp3",
		"id": 41190301
	},
	{
		"time": "20190304",
		"title": "在撒但的攻击下求存（2）",
		"downUrl": "http://txly2.net/ly/audio/2019/it/it190304.mp3",
		"duration": 1760,
		"size": "14.1M",
		"artistId": 41,
		"artistName": "与神同行",
		"path": "https://rawcdn.githack.com/quiet324/LiangYouRadioResource201910/it20190304/it/it190304.mp3",
		"id": 41190304
	},
	{
		"time": "20190305",
		"title": "站立得稳",
		"downUrl": "http://txly2.net/ly/audio/2019/it/it190305.mp3",
		"duration": 1760,
		"size": "14.1M",
		"artistId": 41,
		"artistName": "与神同行",
		"path": "https://rawcdn.githack.com/quiet324/LiangYouRadioResource201910/it20190305/it/it190305.mp3",
		"id": 41190305
	},
	{
		"time": "20190306",
		"title": "灭尽恶者的火箭（1）",
		"downUrl": "http://txly2.net/ly/audio/2019/it/it190306.mp3",
		"duration": 1760,
		"size": "14.1M",
		"artistId": 41,
		"artistName": "与神同行",
		"path": "https://rawcdn.githack.com/quiet324/LiangYouRadioResource201910/it20190306/it/it190306.mp3",
		"id": 41190306
	},
	{
		"time": "20190307",
		"title": "灭尽恶者的火箭（2）",
		"downUrl": "http://txly2.net/ly/audio/2019/it/it190307.mp3",
		"duration": 1760,
		"size": "14.1M",
		"artistId": 41,
		"artistName": "与神同行",
		"path": "https://rawcdn.githack.com/quiet324/LiangYouRadioResource201910/it20190307/it/it190307.mp3",
		"id": 41190307
	},
	{
		"time": "20190308",
		"title": "当信心飘摇时（1）",
		"downUrl": "http://txly2.net/ly/audio/2019/it/it190308.mp3",
		"duration": 1760,
		"size": "14.1M",
		"artistId": 41,
		"artistName": "与神同行",
		"path": "https://rawcdn.githack.com/quiet324/LiangYouRadioResource201910/it20190308/it/it190308.mp3",
		"id": 41190308
	},
	{
		"time": "20190311",
		"title": "当信心飘摇时（2）",
		"downUrl": "http://txly2.net/ly/audio/2019/it/it190311.mp3",
		"duration": 1760,
		"size": "14.1M",
		"artistId": 41,
		"artistName": "与神同行",
		"path": "https://rawcdn.githack.com/quiet324/LiangYouRadioResource201911/it20190311/it/it190311.mp3",
		"id": 41190311
	},
	{
		"time": "20190312",
		"title": "当信心飘摇时（3）",
		"downUrl": "http://txly2.net/ly/audio/2019/it/it190312.mp3",
		"duration": 1760,
		"size": "14.1M",
		"artistId": 41,
		"artistName": "与神同行",
		"path": "https://rawcdn.githack.com/quiet324/LiangYouRadioResource201911/it20190312/it/it190312.mp3",
		"id": 41190312
	},
	{
		"time": "20190313",
		"title": "如何聆听神的话（1）",
		"downUrl": "http://txly2.net/ly/audio/2019/it/it190313.mp3",
		"duration": 1760,
		"size": "14.1M",
		"artistId": 41,
		"artistName": "与神同行",
		"path": "https://rawcdn.githack.com/quiet324/LiangYouRadioResource201911/it20190313/it/it190313.mp3",
		"id": 41190313
	},
	{
		"time": "20190314",
		"title": "如何聆听神的话（2）",
		"downUrl": "http://txly2.net/ly/audio/2019/it/it190314.mp3",
		"duration": 1760,
		"size": "14.1M",
		"artistId": 41,
		"artistName": "与神同行",
		"path": "https://rawcdn.githack.com/quiet324/LiangYouRadioResource201911/it20190314/it/it190314.mp3",
		"id": 41190314
	},
	{
		"time": "20190315",
		"title": "向神祷告（1）",
		"downUrl": "http://txly2.net/ly/audio/2019/it/it190315.mp3",
		"duration": 1760,
		"size": "14.1M",
		"artistId": 41,
		"artistName": "与神同行",
		"path": "https://rawcdn.githack.com/quiet324/LiangYouRadioResource201911/it20190315/it/it190315.mp3",
		"id": 41190315
	},
	{
		"time": "20190318",
		"title": "向神祷告（2）",
		"downUrl": "http://txly2.net/ly/audio/2019/it/it190318.mp3",
		"duration": 1760,
		"size": "14.1M",
		"artistId": 41,
		"artistName": "与神同行",
		"path": "https://rawcdn.githack.com/quiet324/LiangYouRadioResource201912/it20190318/it/it190318.mp3",
		"id": 41190318
	},
	{
		"time": "20190319",
		"title": "不信的恶心",
		"downUrl": "http://txly2.net/ly/audio/2019/it/it190319.mp3",
		"duration": 1760,
		"size": "14.1M",
		"artistId": 41,
		"artistName": "与神同行",
		"path": "https://rawcdn.githack.com/quiet324/LiangYouRadioResource201912/it20190319/it/it190319.mp3",
		"id": 41190319
	},
	{
		"time": "20190320",
		"title": "人生的功课（1）",
		"downUrl": "http://txly2.net/ly/audio/2019/it/it190320.mp3",
		"duration": 1760,
		"size": "14.1M",
		"artistId": 41,
		"artistName": "与神同行",
		"path": "https://rawcdn.githack.com/quiet324/LiangYouRadioResource201912/it20190320/it/it190320.mp3",
		"id": 41190320
	},
	{
		"time": "20190321",
		"title": "人生的功课（2）",
		"downUrl": "http://txly2.net/ly/audio/2019/it/it190321.mp3",
		"duration": 1760,
		"size": "14.1M",
		"artistId": 41,
		"artistName": "与神同行",
		"path": "https://rawcdn.githack.com/quiet324/LiangYouRadioResource201912/it20190321/it/it190321.mp3",
		"id": 41190321
	},
	{
		"time": "20190322",
		"title": "丰盛的人生（1）",
		"downUrl": "http://txly2.net/ly/audio/2019/it/it190322.mp3",
		"duration": 1760,
		"size": "14.1M",
		"artistId": 41,
		"artistName": "与神同行",
		"path": "https://rawcdn.githack.com/quiet324/LiangYouRadioResource201912/it20190322/it/it190322.mp3",
		"id": 41190322
	},
	{
		"time": "20190325",
		"title": "丰盛的人生（2）",
		"downUrl": "http://txly2.net/ly/audio/2019/it/it190325.mp3",
		"duration": 1760,
		"size": "14.1M",
		"artistId": 41,
		"artistName": "与神同行",
		"path": "https://rawcdn.githack.com/quiet324/LiangYouRadioResource201913/it20190325/it/it190325.mp3",
		"id": 41190325
	},
	{
		"time": "20190326",
		"title": "基督徒的工作场所",
		"downUrl": "http://txly2.net/ly/audio/2019/it/it190326.mp3",
		"duration": 1760,
		"size": "14.1M",
		"artistId": 41,
		"artistName": "与神同行",
		"path": "https://rawcdn.githack.com/quiet324/LiangYouRadioResource201913/it20190326/it/it190326.mp3",
		"id": 41190326
	}
]